<?xml version="1.0" encoding="utf-8"?>
<ArrayOfCryptoObject xmlns:xsd="http://www.w3.org/2001/XMLSchema" xmlns:xsi="http://www.w3.org/2001/XMLSchema-instance">
  <CryptoObject>
    <ID>1597a859-a9ea-4e7b-a0a3-4073d6c89097</ID>
    <Exchange>Bittrex</Exchange>
    <SellType>ShortTerm</SellType>
    <Target1>0</Target1>
    <Target2>0</Target2>
    <Target3>0</Target3>
    <Target4>0</Target4>
    <UseTargetsInstreadOfPercentages>false</UseTargetsInstreadOfPercentages>
    <Symbol>ADA</Symbol>
    <StartingAmount>35.9195</StartingAmount>
    <CurrentAmount>0</CurrentAmount>
    <UsedTargets />
    <CurrentRateUSD>0.5941</CurrentRateUSD>
    <CurrentRateBTC>0</CurrentRateBTC>
    <MaxPercentageReached>87.50</MaxPercentageReached>
    <MaxBTCReached>0</MaxBTCReached>
    <TradeAtRateBTC>0.00002778991912470941967455</TradeAtRateBTC>
    <TradeAtRateUSD>0.5182819916766643745040987826</TradeAtRateUSD>
    <TradeAtDateTime>2017-12-18T21:32:48.0095558-06:00</TradeAtDateTime>
    <OrderID>95a4bfa8-746c-4546-a9e2-c2099a9c36d6</OrderID>
    <OrderCompleted>true</OrderCompleted>
    <IsActive>false</IsActive>
    <IsParent>true</IsParent>
    <IsBuyObject>true</IsBuyObject>
    <LastAutoSellTime>0001-01-01T00:00:00</LastAutoSellTime>
    <SoldAllTime>2017-12-18T22:05:36.9971678-06:00</SoldAllTime>
  </CryptoObject>
  <CryptoObject>
    <ID>1597a859-a9ea-4e7b-a0a3-4073d6c89097</ID>
    <Exchange>Bittrex</Exchange>
    <SellType>ShortTerm</SellType>
    <Target1>0</Target1>
    <Target2>0</Target2>
    <Target3>0</Target3>
    <Target4>0</Target4>
    <UseTargetsInstreadOfPercentages>false</UseTargetsInstreadOfPercentages>
    <Symbol>ADA</Symbol>
    <StartingAmount>35.9195</StartingAmount>
    <CurrentAmount>0.0000</CurrentAmount>
    <UsedTargets />
    <CurrentRateUSD>0</CurrentRateUSD>
    <CurrentRateBTC>0</CurrentRateBTC>
    <MaxPercentageReached>0</MaxPercentageReached>
    <MaxBTCReached>0</MaxBTCReached>
    <TradeAtRateBTC>0.0000314998816798674814515792</TradeAtRateBTC>
    <TradeAtRateUSD>0.5937</TradeAtRateUSD>
    <TradeAtDateTime>2017-12-18T22:05:36.0401511-06:00</TradeAtDateTime>
    <OrderID>675ba3b2-e461-42f3-aab9-3f234b218aa1</OrderID>
    <OrderCompleted>true</OrderCompleted>
    <IsActive>true</IsActive>
    <IsParent>false</IsParent>
    <IsBuyObject>false</IsBuyObject>
    <LastAutoSellTime>0001-01-01T00:00:00</LastAutoSellTime>
    <SoldAllTime>0001-01-01T00:00:00</SoldAllTime>
  </CryptoObject>
  <CryptoObject>
    <ID>542d58a0-62ae-4be0-96c9-965a9f32093a</ID>
    <Exchange>Binance</Exchange>
    <SellType>ShortTerm</SellType>
    <Target1>0</Target1>
    <Target2>0</Target2>
    <Target3>0</Target3>
    <Target4>0</Target4>
    <UseTargetsInstreadOfPercentages>false</UseTargetsInstreadOfPercentages>
    <Symbol>STRAT</Symbol>
    <StartingAmount>24.97000000</StartingAmount>
    <CurrentAmount>0</CurrentAmount>
    <UsedTargets />
    <CurrentRateUSD>12.7856753500000000</CurrentRateUSD>
    <CurrentRateBTC>0</CurrentRateBTC>
    <MaxPercentageReached>58.87</MaxPercentageReached>
    <MaxBTCReached>0</MaxBTCReached>
    <TradeAtRateBTC>0.00070100</TradeAtRateBTC>
    <TradeAtRateUSD>13.1200071300000000</TradeAtRateUSD>
    <TradeAtDateTime>2017-12-18T22:12:39.0174361-06:00</TradeAtDateTime>
    <OrderID>4337620</OrderID>
    <OrderCompleted>true</OrderCompleted>
    <IsActive>false</IsActive>
    <IsParent>true</IsParent>
    <IsBuyObject>true</IsBuyObject>
    <LastAutoSellTime>0001-01-01T00:00:00</LastAutoSellTime>
    <SoldAllTime>2017-12-21T16:14:49.707571-06:00</SoldAllTime>
  </CryptoObject>
  <CryptoObject>
    <ID>f8d47136-1269-4b94-bfd9-aacb9b661d2f</ID>
    <Exchange>Binance</Exchange>
    <SellType>ShortTerm</SellType>
    <Target1>0</Target1>
    <Target2>0</Target2>
    <Target3>0</Target3>
    <Target4>0</Target4>
    <UseTargetsInstreadOfPercentages>false</UseTargetsInstreadOfPercentages>
    <Symbol>XRP</Symbol>
    <StartingAmount>1000.00000000</StartingAmount>
    <CurrentAmount>0.00000000</CurrentAmount>
    <UsedTargets />
    <CurrentRateUSD>0.9285745499000000</CurrentRateUSD>
    <CurrentRateBTC>0</CurrentRateBTC>
    <MaxPercentageReached>89.42</MaxPercentageReached>
    <MaxBTCReached>0</MaxBTCReached>
    <TradeAtRateBTC>0.00004270</TradeAtRateBTC>
    <TradeAtRateUSD>0.7990878000000000</TradeAtRateUSD>
    <TradeAtDateTime>2017-12-18T22:14:27.9723824-06:00</TradeAtDateTime>
    <OrderID>4607463</OrderID>
    <OrderCompleted>true</OrderCompleted>
    <IsActive>false</IsActive>
    <IsParent>true</IsParent>
    <IsBuyObject>true</IsBuyObject>
    <LastAutoSellTime>2017-12-21T01:03:11.0958182-06:00</LastAutoSellTime>
    <SoldAllTime>2017-12-21T01:03:16.9369256-06:00</SoldAllTime>
  </CryptoObject>
  <CryptoObject>
    <ID>81a86045-561f-4e9f-9fa3-ce811d79785f</ID>
    <Exchange>Bittrex</Exchange>
    <SellType>ShortTerm</SellType>
    <Target1>0</Target1>
    <Target2>0</Target2>
    <Target3>0</Target3>
    <Target4>0</Target4>
    <UseTargetsInstreadOfPercentages>false</UseTargetsInstreadOfPercentages>
    <Symbol>EDG</Symbol>
    <StartingAmount>200</StartingAmount>
    <CurrentAmount>0</CurrentAmount>
    <UsedTargets />
    <CurrentRateUSD>1.5296324</CurrentRateUSD>
    <CurrentRateBTC>0</CurrentRateBTC>
    <MaxPercentageReached>5.39</MaxPercentageReached>
    <MaxBTCReached>0</MaxBTCReached>
    <TradeAtRateBTC>0.000105</TradeAtRateBTC>
    <TradeAtRateUSD>1.97201287500105</TradeAtRateUSD>
    <TradeAtDateTime>2017-12-18T22:16:58.3603219-06:00</TradeAtDateTime>
    <OrderID>fd06f202-48dc-46cf-be22-0a2a8ccac56a</OrderID>
    <OrderCompleted>true</OrderCompleted>
    <IsActive>false</IsActive>
    <IsParent>true</IsParent>
    <IsBuyObject>true</IsBuyObject>
    <LastAutoSellTime>0001-01-01T00:00:00</LastAutoSellTime>
    <SoldAllTime>2017-12-22T15:40:46.8847959-06:00</SoldAllTime>
  </CryptoObject>
  <CryptoObject>
    <ID>11cccc60-48ed-4fba-a940-c734277508ed</ID>
    <Exchange>Bittrex</Exchange>
    <SellType>ShortTerm</SellType>
    <Target1>0</Target1>
    <Target2>0</Target2>
    <Target3>0</Target3>
    <Target4>0</Target4>
    <UseTargetsInstreadOfPercentages>false</UseTargetsInstreadOfPercentages>
    <Symbol>POT</Symbol>
    <StartingAmount>1000</StartingAmount>
    <CurrentAmount>0</CurrentAmount>
    <UsedTargets />
    <CurrentRateUSD>0.2932996000466422</CurrentRateUSD>
    <CurrentRateBTC>0</CurrentRateBTC>
    <MaxPercentageReached>14.89</MaxPercentageReached>
    <MaxBTCReached>0</MaxBTCReached>
    <TradeAtRateBTC>0.00002001</TradeAtRateBTC>
    <TradeAtRateUSD>0.3758093107502001</TradeAtRateUSD>
    <TradeAtDateTime>2017-12-18T22:20:41.7861952-06:00</TradeAtDateTime>
    <OrderID>30dd7f8e-3fb2-4d44-b8c2-9e320b82ea1e</OrderID>
    <OrderCompleted>true</OrderCompleted>
    <IsActive>false</IsActive>
    <IsParent>true</IsParent>
    <IsBuyObject>true</IsBuyObject>
    <LastAutoSellTime>2017-12-22T14:22:59.4979771-06:00</LastAutoSellTime>
    <SoldAllTime>2017-12-22T16:23:00.794572-06:00</SoldAllTime>
  </CryptoObject>
  <CryptoObject>
    <ID>e6e27557-77d8-41ee-83d4-2224d7dad0bf</ID>
    <Exchange>Bittrex</Exchange>
    <SellType>ShortTerm</SellType>
    <Target1>0</Target1>
    <Target2>0</Target2>
    <Target3>0</Target3>
    <Target4>0</Target4>
    <UseTargetsInstreadOfPercentages>false</UseTargetsInstreadOfPercentages>
    <Symbol>GAME</Symbol>
    <StartingAmount>75</StartingAmount>
    <CurrentAmount>0</CurrentAmount>
    <UsedTargets />
    <CurrentRateUSD>3.67923600</CurrentRateUSD>
    <CurrentRateBTC>0</CurrentRateBTC>
    <MaxPercentageReached>74.40</MaxPercentageReached>
    <MaxBTCReached>0</MaxBTCReached>
    <TradeAtRateBTC>0.0001850198666666666666666667</TradeAtRateBTC>
    <TradeAtRateUSD>3.4783734933351835320000006267</TradeAtRateUSD>
    <TradeAtDateTime>2017-12-18T22:25:24.0975982-06:00</TradeAtDateTime>
    <OrderID>97240041-7117-493f-8073-d9ba083305ff</OrderID>
    <OrderCompleted>true</OrderCompleted>
    <IsActive>false</IsActive>
    <IsParent>true</IsParent>
    <IsBuyObject>true</IsBuyObject>
    <LastAutoSellTime>0001-01-01T00:00:00</LastAutoSellTime>
    <SoldAllTime>2017-12-21T11:58:29.8728222-06:00</SoldAllTime>
  </CryptoObject>
  <CryptoObject>
    <ID>6bc227f5-057b-4d45-a5bd-985b3d885ffe</ID>
    <Exchange>Bittrex</Exchange>
    <SellType>ShortTerm</SellType>
    <Target1>0</Target1>
    <Target2>0</Target2>
    <Target3>0</Target3>
    <Target4>0</Target4>
    <UseTargetsInstreadOfPercentages>false</UseTargetsInstreadOfPercentages>
    <Symbol>QRL</Symbol>
    <StartingAmount>15</StartingAmount>
    <CurrentAmount>0</CurrentAmount>
    <UsedTargets />
    <CurrentRateUSD>1.75101592</CurrentRateUSD>
    <CurrentRateBTC>0</CurrentRateBTC>
    <MaxPercentageReached>62.68</MaxPercentageReached>
    <MaxBTCReached>0</MaxBTCReached>
    <TradeAtRateBTC>0.0000944</TradeAtRateBTC>
    <TradeAtRateUSD>1.7747200</TradeAtRateUSD>
    <TradeAtDateTime>2017-12-18T22:25:11.674743-06:00</TradeAtDateTime>
    <OrderID>0fba1bd1-d52d-42d9-8f01-5090149ead07</OrderID>
    <OrderCompleted>true</OrderCompleted>
    <IsActive>false</IsActive>
    <IsParent>true</IsParent>
    <IsBuyObject>true</IsBuyObject>
    <LastAutoSellTime>0001-01-01T00:00:00</LastAutoSellTime>
    <SoldAllTime>2017-12-21T15:00:09.675692-06:00</SoldAllTime>
  </CryptoObject>
  <CryptoObject>
    <ID>a6e9f4d1-fea9-473d-9384-76091deee94b</ID>
    <Exchange>Binance</Exchange>
    <SellType>ShortTerm</SellType>
    <Target1>0</Target1>
    <Target2>0</Target2>
    <Target3>0</Target3>
    <Target4>0</Target4>
    <UseTargetsInstreadOfPercentages>false</UseTargetsInstreadOfPercentages>
    <Symbol>LEND</Symbol>
    <StartingAmount>4995.00000000</StartingAmount>
    <CurrentAmount>0.00000000</CurrentAmount>
    <UsedTargets />
    <CurrentRateUSD>0.0597377984000000</CurrentRateUSD>
    <CurrentRateBTC>0</CurrentRateBTC>
    <MaxPercentageReached>20.73</MaxPercentageReached>
    <MaxBTCReached>0</MaxBTCReached>
    <TradeAtRateBTC>0.00000427</TradeAtRateBTC>
    <TradeAtRateUSD>0.0796636820000000</TradeAtRateUSD>
    <TradeAtDateTime>2017-12-18T22:43:10.1734127-06:00</TradeAtDateTime>
    <OrderID>485963</OrderID>
    <OrderCompleted>true</OrderCompleted>
    <IsActive>false</IsActive>
    <IsParent>true</IsParent>
    <IsBuyObject>true</IsBuyObject>
    <LastAutoSellTime>0001-01-01T00:00:00</LastAutoSellTime>
    <SoldAllTime>2017-12-23T21:55:11.1431885-06:00</SoldAllTime>
  </CryptoObject>
  <CryptoObject>
    <ID>c66a07bc-284a-481d-8f9e-d1166c1d3155</ID>
    <Exchange>Bittrex</Exchange>
    <SellType>ShortTerm</SellType>
    <Target1>0</Target1>
    <Target2>0</Target2>
    <Target3>0</Target3>
    <Target4>0</Target4>
    <UseTargetsInstreadOfPercentages>false</UseTargetsInstreadOfPercentages>
    <Symbol>XLM</Symbol>
    <StartingAmount>2000</StartingAmount>
    <CurrentAmount>0</CurrentAmount>
    <UsedTargets />
    <CurrentRateUSD>0.231379194972030</CurrentRateUSD>
    <CurrentRateBTC>0</CurrentRateBTC>
    <MaxPercentageReached>37.86</MaxPercentageReached>
    <MaxBTCReached>0</MaxBTCReached>
    <TradeAtRateBTC>0.00001472</TradeAtRateBTC>
    <TradeAtRateUSD>0.24508800</TradeAtRateUSD>
    <TradeAtDateTime>2017-12-20T12:21:34.4849513-06:00</TradeAtDateTime>
    <OrderID>85029a76-b227-46e4-89e1-3795840be3ae</OrderID>
    <OrderCompleted>true</OrderCompleted>
    <IsActive>false</IsActive>
    <IsParent>true</IsParent>
    <IsBuyObject>true</IsBuyObject>
    <LastAutoSellTime>2017-12-21T20:45:33.1351679-06:00</LastAutoSellTime>
    <SoldAllTime>2017-12-21T21:18:57.486747-06:00</SoldAllTime>
  </CryptoObject>
  <CryptoObject>
    <ID>de0b77c1-5dbe-4f0c-b790-174360bd8cfd</ID>
    <Exchange>Bittrex</Exchange>
    <SellType>ShortTerm</SellType>
    <Target1>0</Target1>
    <Target2>0</Target2>
    <Target3>0</Target3>
    <Target4>0</Target4>
    <UseTargetsInstreadOfPercentages>false</UseTargetsInstreadOfPercentages>
    <Symbol>REP</Symbol>
    <StartingAmount>5</StartingAmount>
    <CurrentAmount>0.0</CurrentAmount>
    <UsedTargets />
    <CurrentRateUSD>87.99905934</CurrentRateUSD>
    <CurrentRateBTC>0</CurrentRateBTC>
    <MaxPercentageReached>46.57</MaxPercentageReached>
    <MaxBTCReached>0</MaxBTCReached>
    <TradeAtRateBTC>0.005265528</TradeAtRateBTC>
    <TradeAtRateUSD>87.997503936</TradeAtRateUSD>
    <TradeAtDateTime>2017-12-20T12:52:23.5227775-06:00</TradeAtDateTime>
    <OrderID>3b845a1d-179f-41cf-9ba5-6e93c9ac457b</OrderID>
    <OrderCompleted>true</OrderCompleted>
    <IsActive>false</IsActive>
    <IsParent>true</IsParent>
    <IsBuyObject>true</IsBuyObject>
    <LastAutoSellTime>2017-12-21T08:28:16.5133713-06:00</LastAutoSellTime>
    <SoldAllTime>2017-12-21T08:28:32.8561805-06:00</SoldAllTime>
  </CryptoObject>
  <CryptoObject>
    <ID>3993550b-1677-471a-98c1-05690d5d22a2</ID>
    <Exchange>Bittrex</Exchange>
    <SellType>ShortTerm</SellType>
    <Target1>0</Target1>
    <Target2>0</Target2>
    <Target3>0</Target3>
    <Target4>0</Target4>
    <UseTargetsInstreadOfPercentages>false</UseTargetsInstreadOfPercentages>
    <Symbol>BLITZ</Symbol>
    <StartingAmount>50</StartingAmount>
    <CurrentAmount>0</CurrentAmount>
    <UsedTargets />
    <CurrentRateUSD>2.05247402</CurrentRateUSD>
    <CurrentRateBTC>0</CurrentRateBTC>
    <MaxPercentageReached>20.75</MaxPercentageReached>
    <MaxBTCReached>0</MaxBTCReached>
    <TradeAtRateBTC>0.0001589496</TradeAtRateBTC>
    <TradeAtRateUSD>2.646773479432167864</TradeAtRateUSD>
    <TradeAtDateTime>2017-12-20T13:07:27.8150114-06:00</TradeAtDateTime>
    <OrderID>b455116d-67f7-4f01-95d6-279c3f772a7a</OrderID>
    <OrderCompleted>true</OrderCompleted>
    <IsActive>false</IsActive>
    <IsParent>true</IsParent>
    <IsBuyObject>true</IsBuyObject>
    <LastAutoSellTime>0001-01-01T00:00:00</LastAutoSellTime>
    <SoldAllTime>2017-12-22T08:53:00.4541695-06:00</SoldAllTime>
  </CryptoObject>
  <CryptoObject>
    <ID>de0b77c1-5dbe-4f0c-b790-174360bd8cfd</ID>
    <Exchange>Bittrex</Exchange>
    <SellType>ShortTerm</SellType>
    <Target1>0</Target1>
    <Target2>0</Target2>
    <Target3>0</Target3>
    <Target4>0</Target4>
    <UseTargetsInstreadOfPercentages>false</UseTargetsInstreadOfPercentages>
    <Symbol>REP</Symbol>
    <StartingAmount>5</StartingAmount>
    <CurrentAmount>3.5</CurrentAmount>
    <UsedTargets />
    <CurrentRateUSD>0</CurrentRateUSD>
    <CurrentRateBTC>0</CurrentRateBTC>
    <MaxPercentageReached>0</MaxPercentageReached>
    <MaxBTCReached>0</MaxBTCReached>
    <TradeAtRateBTC>0.0064549466666666666666666667</TradeAtRateBTC>
    <TradeAtRateUSD>106.1839</TradeAtRateUSD>
    <TradeAtDateTime>2017-12-20T18:08:42.7114548-06:00</TradeAtDateTime>
    <OrderID>894edefe-933a-4799-ad72-5dd4314789dd</OrderID>
    <OrderCompleted>true</OrderCompleted>
    <IsActive>true</IsActive>
    <IsParent>false</IsParent>
    <IsBuyObject>false</IsBuyObject>
    <LastAutoSellTime>0001-01-01T00:00:00</LastAutoSellTime>
    <SoldAllTime>0001-01-01T00:00:00</SoldAllTime>
  </CryptoObject>
  <CryptoObject>
    <ID>f8d47136-1269-4b94-bfd9-aacb9b661d2f</ID>
    <Exchange>Binance</Exchange>
    <SellType>ShortTerm</SellType>
    <Target1>0</Target1>
    <Target2>0</Target2>
    <Target3>0</Target3>
    <Target4>0</Target4>
    <UseTargetsInstreadOfPercentages>false</UseTargetsInstreadOfPercentages>
    <Symbol>XRP</Symbol>
    <StartingAmount>1000.00000000</StartingAmount>
    <CurrentAmount>700.00000000</CurrentAmount>
    <UsedTargets />
    <CurrentRateUSD>0</CurrentRateUSD>
    <CurrentRateBTC>0</CurrentRateBTC>
    <MaxPercentageReached>0</MaxPercentageReached>
    <MaxBTCReached>0</MaxBTCReached>
    <TradeAtRateBTC>0.00005690</TradeAtRateBTC>
    <TradeAtRateUSD>0.9366092780000000</TradeAtRateUSD>
    <TradeAtDateTime>2017-12-20T21:23:08.3209534-06:00</TradeAtDateTime>
    <OrderID>5114304</OrderID>
    <OrderCompleted>true</OrderCompleted>
    <IsActive>true</IsActive>
    <IsParent>false</IsParent>
    <IsBuyObject>false</IsBuyObject>
    <LastAutoSellTime>0001-01-01T00:00:00</LastAutoSellTime>
    <SoldAllTime>0001-01-01T00:00:00</SoldAllTime>
  </CryptoObject>
  <CryptoObject>
    <ID>f8d47136-1269-4b94-bfd9-aacb9b661d2f</ID>
    <Exchange>Binance</Exchange>
    <SellType>ShortTerm</SellType>
    <Target1>0</Target1>
    <Target2>0</Target2>
    <Target3>0</Target3>
    <Target4>0</Target4>
    <UseTargetsInstreadOfPercentages>false</UseTargetsInstreadOfPercentages>
    <Symbol>XRP</Symbol>
    <StartingAmount>700.00000000</StartingAmount>
    <CurrentAmount>400.00000000</CurrentAmount>
    <UsedTargets />
    <CurrentRateUSD>0</CurrentRateUSD>
    <CurrentRateBTC>0</CurrentRateBTC>
    <MaxPercentageReached>0</MaxPercentageReached>
    <MaxBTCReached>0</MaxBTCReached>
    <TradeAtRateBTC>0.00005526</TradeAtRateBTC>
    <TradeAtRateUSD>0.9321251274000000</TradeAtRateUSD>
    <TradeAtDateTime>2017-12-20T22:23:18.8550412-06:00</TradeAtDateTime>
    <OrderID>5145017</OrderID>
    <OrderCompleted>true</OrderCompleted>
    <IsActive>true</IsActive>
    <IsParent>false</IsParent>
    <IsBuyObject>false</IsBuyObject>
    <LastAutoSellTime>0001-01-01T00:00:00</LastAutoSellTime>
    <SoldAllTime>0001-01-01T00:00:00</SoldAllTime>
  </CryptoObject>
  <CryptoObject>
    <ID>f8d47136-1269-4b94-bfd9-aacb9b661d2f</ID>
    <Exchange>Binance</Exchange>
    <SellType>ShortTerm</SellType>
    <Target1>0</Target1>
    <Target2>0</Target2>
    <Target3>0</Target3>
    <Target4>0</Target4>
    <UseTargetsInstreadOfPercentages>false</UseTargetsInstreadOfPercentages>
    <Symbol>XRP</Symbol>
    <StartingAmount>400.00000000</StartingAmount>
    <CurrentAmount>100.00000000</CurrentAmount>
    <UsedTargets />
    <CurrentRateUSD>0</CurrentRateUSD>
    <CurrentRateBTC>0</CurrentRateBTC>
    <MaxPercentageReached>0</MaxPercentageReached>
    <MaxBTCReached>0</MaxBTCReached>
    <TradeAtRateBTC>0.00005741</TradeAtRateBTC>
    <TradeAtRateUSD>0.9629281703000000</TradeAtRateUSD>
    <TradeAtDateTime>2017-12-21T00:03:03.9937198-06:00</TradeAtDateTime>
    <OrderID>5176632</OrderID>
    <OrderCompleted>true</OrderCompleted>
    <IsActive>true</IsActive>
    <IsParent>false</IsParent>
    <IsBuyObject>false</IsBuyObject>
    <LastAutoSellTime>0001-01-01T00:00:00</LastAutoSellTime>
    <SoldAllTime>0001-01-01T00:00:00</SoldAllTime>
  </CryptoObject>
  <CryptoObject>
    <ID>f8d47136-1269-4b94-bfd9-aacb9b661d2f</ID>
    <Exchange>Binance</Exchange>
    <SellType>ShortTerm</SellType>
    <Target1>0</Target1>
    <Target2>0</Target2>
    <Target3>0</Target3>
    <Target4>0</Target4>
    <UseTargetsInstreadOfPercentages>false</UseTargetsInstreadOfPercentages>
    <Symbol>XRP</Symbol>
    <StartingAmount>100.00000000</StartingAmount>
    <CurrentAmount>0.00000000</CurrentAmount>
    <UsedTargets />
    <CurrentRateUSD>0</CurrentRateUSD>
    <CurrentRateBTC>0</CurrentRateBTC>
    <MaxPercentageReached>0</MaxPercentageReached>
    <MaxBTCReached>0</MaxBTCReached>
    <TradeAtRateBTC>0.00005393</TradeAtRateBTC>
    <TradeAtRateUSD>0.9275426093000000</TradeAtRateUSD>
    <TradeAtDateTime>2017-12-21T01:03:14.1086155-06:00</TradeAtDateTime>
    <OrderID>5194419</OrderID>
    <OrderCompleted>true</OrderCompleted>
    <IsActive>true</IsActive>
    <IsParent>false</IsParent>
    <IsBuyObject>false</IsBuyObject>
    <LastAutoSellTime>0001-01-01T00:00:00</LastAutoSellTime>
    <SoldAllTime>0001-01-01T00:00:00</SoldAllTime>
  </CryptoObject>
  <CryptoObject>
    <ID>de0b77c1-5dbe-4f0c-b790-174360bd8cfd</ID>
    <Exchange>Bittrex</Exchange>
    <SellType>ShortTerm</SellType>
    <Target1>0</Target1>
    <Target2>0</Target2>
    <Target3>0</Target3>
    <Target4>0</Target4>
    <UseTargetsInstreadOfPercentages>false</UseTargetsInstreadOfPercentages>
    <Symbol>REP</Symbol>
    <StartingAmount>3.5</StartingAmount>
    <CurrentAmount>0.0</CurrentAmount>
    <UsedTargets />
    <CurrentRateUSD>0</CurrentRateUSD>
    <CurrentRateBTC>0</CurrentRateBTC>
    <MaxPercentageReached>0</MaxPercentageReached>
    <MaxBTCReached>0</MaxBTCReached>
    <TradeAtRateBTC>0.0054156571428571428571428571</TradeAtRateBTC>
    <TradeAtRateUSD>87.9990</TradeAtRateUSD>
    <TradeAtDateTime>2017-12-21T08:28:32.8369901-06:00</TradeAtDateTime>
    <OrderID>4e7cb90d-78c2-4ee7-a1f2-7281f04dff54</OrderID>
    <OrderCompleted>true</OrderCompleted>
    <IsActive>true</IsActive>
    <IsParent>false</IsParent>
    <IsBuyObject>false</IsBuyObject>
    <LastAutoSellTime>0001-01-01T00:00:00</LastAutoSellTime>
    <SoldAllTime>0001-01-01T00:00:00</SoldAllTime>
  </CryptoObject>
  <CryptoObject>
    <ID>e6e27557-77d8-41ee-83d4-2224d7dad0bf</ID>
    <Exchange>Bittrex</Exchange>
    <SellType>ShortTerm</SellType>
    <Target1>0</Target1>
    <Target2>0</Target2>
    <Target3>0</Target3>
    <Target4>0</Target4>
    <UseTargetsInstreadOfPercentages>false</UseTargetsInstreadOfPercentages>
    <Symbol>GAME</Symbol>
    <StartingAmount>75</StartingAmount>
    <CurrentAmount>0</CurrentAmount>
    <UsedTargets />
    <CurrentRateUSD>0</CurrentRateUSD>
    <CurrentRateBTC>0</CurrentRateBTC>
    <MaxPercentageReached>0</MaxPercentageReached>
    <MaxBTCReached>0</MaxBTCReached>
    <TradeAtRateBTC>0.0002477598666666666666666667</TradeAtRateBTC>
    <TradeAtRateUSD>3.6569357558799333333333338253</TradeAtRateUSD>
    <TradeAtDateTime>2017-12-21T11:58:29.5387893-06:00</TradeAtDateTime>
    <OrderID>396d0632-3b85-4a90-8cbf-a62aed51d2b0</OrderID>
    <OrderCompleted>true</OrderCompleted>
    <IsActive>true</IsActive>
    <IsParent>false</IsParent>
    <IsBuyObject>false</IsBuyObject>
    <LastAutoSellTime>0001-01-01T00:00:00</LastAutoSellTime>
    <SoldAllTime>0001-01-01T00:00:00</SoldAllTime>
  </CryptoObject>
  <CryptoObject>
    <ID>6bc227f5-057b-4d45-a5bd-985b3d885ffe</ID>
    <Exchange>Bittrex</Exchange>
    <SellType>ShortTerm</SellType>
    <Target1>0</Target1>
    <Target2>0</Target2>
    <Target3>0</Target3>
    <Target4>0</Target4>
    <UseTargetsInstreadOfPercentages>false</UseTargetsInstreadOfPercentages>
    <Symbol>QRL</Symbol>
    <StartingAmount>15</StartingAmount>
    <CurrentAmount>0</CurrentAmount>
    <UsedTargets />
    <CurrentRateUSD>0</CurrentRateUSD>
    <CurrentRateBTC>0</CurrentRateBTC>
    <MaxPercentageReached>0</MaxPercentageReached>
    <MaxBTCReached>0</MaxBTCReached>
    <TradeAtRateBTC>0.00011848</TradeAtRateBTC>
    <TradeAtRateUSD>1.7510</TradeAtRateUSD>
    <TradeAtDateTime>2017-12-21T15:00:09.6694713-06:00</TradeAtDateTime>
    <OrderID>659b4701-7511-438a-974e-28bb21573bad</OrderID>
    <OrderCompleted>true</OrderCompleted>
    <IsActive>true</IsActive>
    <IsParent>false</IsParent>
    <IsBuyObject>false</IsBuyObject>
    <LastAutoSellTime>0001-01-01T00:00:00</LastAutoSellTime>
    <SoldAllTime>0001-01-01T00:00:00</SoldAllTime>
  </CryptoObject>
  <CryptoObject>
    <ID>542d58a0-62ae-4be0-96c9-965a9f32093a</ID>
    <Exchange>Binance</Exchange>
    <SellType>ShortTerm</SellType>
    <Target1>0</Target1>
    <Target2>0</Target2>
    <Target3>0</Target3>
    <Target4>0</Target4>
    <UseTargetsInstreadOfPercentages>false</UseTargetsInstreadOfPercentages>
    <Symbol>STRAT</Symbol>
    <StartingAmount>24.97000000</StartingAmount>
    <CurrentAmount>0.00000000</CurrentAmount>
    <UsedTargets />
    <CurrentRateUSD>0</CurrentRateUSD>
    <CurrentRateBTC>0</CurrentRateBTC>
    <MaxPercentageReached>0</MaxPercentageReached>
    <MaxBTCReached>0</MaxBTCReached>
    <TradeAtRateBTC>0.00083400</TradeAtRateBTC>
    <TradeAtRateUSD>12.8010243000000000</TradeAtRateUSD>
    <TradeAtDateTime>2017-12-21T16:14:48.7037685-06:00</TradeAtDateTime>
    <OrderID>4542085</OrderID>
    <OrderCompleted>true</OrderCompleted>
    <IsActive>true</IsActive>
    <IsParent>false</IsParent>
    <IsBuyObject>false</IsBuyObject>
    <LastAutoSellTime>0001-01-01T00:00:00</LastAutoSellTime>
    <SoldAllTime>0001-01-01T00:00:00</SoldAllTime>
  </CryptoObject>
  <CryptoObject>
    <ID>c66a07bc-284a-481d-8f9e-d1166c1d3155</ID>
    <Exchange>Bittrex</Exchange>
    <SellType>ShortTerm</SellType>
    <Target1>0</Target1>
    <Target2>0</Target2>
    <Target3>0</Target3>
    <Target4>0</Target4>
    <UseTargetsInstreadOfPercentages>false</UseTargetsInstreadOfPercentages>
    <Symbol>XLM</Symbol>
    <StartingAmount>2000</StartingAmount>
    <CurrentAmount>1000</CurrentAmount>
    <UsedTargets />
    <CurrentRateUSD>0</CurrentRateUSD>
    <CurrentRateBTC>0</CurrentRateBTC>
    <MaxPercentageReached>0</MaxPercentageReached>
    <MaxBTCReached>0</MaxBTCReached>
    <TradeAtRateBTC>0.00001766</TradeAtRateBTC>
    <TradeAtRateUSD>0.2499</TradeAtRateUSD>
    <TradeAtDateTime>2017-12-21T20:45:55.8244907-06:00</TradeAtDateTime>
    <OrderID>5fec0cab-97da-4cc7-bcb5-e34eb9a4441a</OrderID>
    <OrderCompleted>true</OrderCompleted>
    <IsActive>true</IsActive>
    <IsParent>false</IsParent>
    <IsBuyObject>false</IsBuyObject>
    <LastAutoSellTime>0001-01-01T00:00:00</LastAutoSellTime>
    <SoldAllTime>0001-01-01T00:00:00</SoldAllTime>
  </CryptoObject>
  <CryptoObject>
    <ID>c66a07bc-284a-481d-8f9e-d1166c1d3155</ID>
    <Exchange>Bittrex</Exchange>
    <SellType>ShortTerm</SellType>
    <Target1>0</Target1>
    <Target2>0</Target2>
    <Target3>0</Target3>
    <Target4>0</Target4>
    <UseTargetsInstreadOfPercentages>false</UseTargetsInstreadOfPercentages>
    <Symbol>XLM</Symbol>
    <StartingAmount>1000</StartingAmount>
    <CurrentAmount>0</CurrentAmount>
    <UsedTargets />
    <CurrentRateUSD>0</CurrentRateUSD>
    <CurrentRateBTC>0</CurrentRateBTC>
    <MaxPercentageReached>0</MaxPercentageReached>
    <MaxBTCReached>0</MaxBTCReached>
    <TradeAtRateBTC>0.0000174</TradeAtRateBTC>
    <TradeAtRateUSD>0.2314</TradeAtRateUSD>
    <TradeAtDateTime>2017-12-21T21:18:57.478742-06:00</TradeAtDateTime>
    <OrderID>84b6f9c4-1d4a-4e74-a40b-01d2c677fc8d</OrderID>
    <OrderCompleted>true</OrderCompleted>
    <IsActive>true</IsActive>
    <IsParent>false</IsParent>
    <IsBuyObject>false</IsBuyObject>
    <LastAutoSellTime>0001-01-01T00:00:00</LastAutoSellTime>
    <SoldAllTime>0001-01-01T00:00:00</SoldAllTime>
  </CryptoObject>
  <CryptoObject>
    <ID>edd22d41-3e62-4c7d-b6e9-2c5a2b8e7766</ID>
    <Exchange>Bittrex</Exchange>
    <SellType>ShortTerm</SellType>
    <Target1>0</Target1>
    <Target2>0</Target2>
    <Target3>0</Target3>
    <Target4>0</Target4>
    <UseTargetsInstreadOfPercentages>false</UseTargetsInstreadOfPercentages>
    <Symbol>ADA</Symbol>
    <StartingAmount>35</StartingAmount>
    <CurrentAmount>0</CurrentAmount>
    <UsedTargets />
    <CurrentRateUSD>0.418549104227030</CurrentRateUSD>
    <CurrentRateBTC>0</CurrentRateBTC>
    <MaxPercentageReached>24.82</MaxPercentageReached>
    <MaxBTCReached>0</MaxBTCReached>
    <TradeAtRateBTC>0.00002941</TradeAtRateBTC>
    <TradeAtRateUSD>0.4032111000002941</TradeAtRateUSD>
    <TradeAtDateTime>2017-12-21T21:40:04.4978125-06:00</TradeAtDateTime>
    <OrderID>f3e39f76-0183-4404-9bb4-a9e3a10ac24f</OrderID>
    <OrderCompleted>true</OrderCompleted>
    <IsActive>false</IsActive>
    <IsParent>true</IsParent>
    <IsBuyObject>true</IsBuyObject>
    <LastAutoSellTime>0001-01-01T00:00:00</LastAutoSellTime>
    <SoldAllTime>2017-12-21T22:18:23.5995264-06:00</SoldAllTime>
  </CryptoObject>
  <CryptoObject>
    <ID>edd22d41-3e62-4c7d-b6e9-2c5a2b8e7766</ID>
    <Exchange>Bittrex</Exchange>
    <SellType>ShortTerm</SellType>
    <Target1>0</Target1>
    <Target2>0</Target2>
    <Target3>0</Target3>
    <Target4>0</Target4>
    <UseTargetsInstreadOfPercentages>false</UseTargetsInstreadOfPercentages>
    <Symbol>ADA</Symbol>
    <StartingAmount>35</StartingAmount>
    <CurrentAmount>0</CurrentAmount>
    <UsedTargets />
    <CurrentRateUSD>0</CurrentRateUSD>
    <CurrentRateBTC>0</CurrentRateBTC>
    <MaxPercentageReached>0</MaxPercentageReached>
    <MaxBTCReached>0</MaxBTCReached>
    <TradeAtRateBTC>0.00002954</TradeAtRateBTC>
    <TradeAtRateUSD>0.4185</TradeAtRateUSD>
    <TradeAtDateTime>2017-12-21T22:18:23.5915204-06:00</TradeAtDateTime>
    <OrderID>ef93b02a-2400-4902-8b6a-75f08a77e8f1</OrderID>
    <OrderCompleted>true</OrderCompleted>
    <IsActive>true</IsActive>
    <IsParent>false</IsParent>
    <IsBuyObject>false</IsBuyObject>
    <LastAutoSellTime>0001-01-01T00:00:00</LastAutoSellTime>
    <SoldAllTime>0001-01-01T00:00:00</SoldAllTime>
  </CryptoObject>
  <CryptoObject>
    <ID>18a2832f-539c-42a9-8505-6c05c395b49f</ID>
    <Exchange>Bittrex</Exchange>
    <SellType>ShortTerm</SellType>
    <Target1>0</Target1>
    <Target2>0</Target2>
    <Target3>0</Target3>
    <Target4>0</Target4>
    <UseTargetsInstreadOfPercentages>false</UseTargetsInstreadOfPercentages>
    <Symbol>STRAT</Symbol>
    <StartingAmount>5</StartingAmount>
    <CurrentAmount>0</CurrentAmount>
    <UsedTargets />
    <CurrentRateUSD>10.13701680</CurrentRateUSD>
    <CurrentRateBTC>0</CurrentRateBTC>
    <MaxPercentageReached>20.10</MaxPercentageReached>
    <MaxBTCReached>0</MaxBTCReached>
    <TradeAtRateBTC>0.00074026</TradeAtRateBTC>
    <TradeAtRateUSD>10.12675680</TradeAtRateUSD>
    <TradeAtDateTime>2017-12-22T00:06:49.9037604-06:00</TradeAtDateTime>
    <OrderID>a5d34ab3-846b-4c63-8ac8-5492663cd9c8</OrderID>
    <OrderCompleted>true</OrderCompleted>
    <IsActive>false</IsActive>
    <IsParent>true</IsParent>
    <IsBuyObject>true</IsBuyObject>
    <LastAutoSellTime>0001-01-01T00:00:00</LastAutoSellTime>
    <SoldAllTime>2017-12-22T00:08:19.8029105-06:00</SoldAllTime>
  </CryptoObject>
  <CryptoObject>
    <ID>18a2832f-539c-42a9-8505-6c05c395b49f</ID>
    <Exchange>Bittrex</Exchange>
    <SellType>ShortTerm</SellType>
    <Target1>0</Target1>
    <Target2>0</Target2>
    <Target3>0</Target3>
    <Target4>0</Target4>
    <UseTargetsInstreadOfPercentages>false</UseTargetsInstreadOfPercentages>
    <Symbol>STRAT</Symbol>
    <StartingAmount>5</StartingAmount>
    <CurrentAmount>0</CurrentAmount>
    <UsedTargets />
    <CurrentRateUSD>0</CurrentRateUSD>
    <CurrentRateBTC>0</CurrentRateBTC>
    <MaxPercentageReached>0</MaxPercentageReached>
    <MaxBTCReached>0</MaxBTCReached>
    <TradeAtRateBTC>0.000741008</TradeAtRateBTC>
    <TradeAtRateUSD>10.136989440</TradeAtRateUSD>
    <TradeAtDateTime>2017-12-22T00:08:19.7833941-06:00</TradeAtDateTime>
    <OrderID>e94b6bee-8426-4b17-946f-e68db348fa3a</OrderID>
    <OrderCompleted>true</OrderCompleted>
    <IsActive>true</IsActive>
    <IsParent>false</IsParent>
    <IsBuyObject>false</IsBuyObject>
    <LastAutoSellTime>0001-01-01T00:00:00</LastAutoSellTime>
    <SoldAllTime>0001-01-01T00:00:00</SoldAllTime>
  </CryptoObject>
  <CryptoObject>
    <ID>f4648cfe-198d-4488-85f5-f17618269eca</ID>
    <Exchange>Binance</Exchange>
    <SellType>ShortTerm</SellType>
    <Target1>0</Target1>
    <Target2>0</Target2>
    <Target3>0</Target3>
    <Target4>0</Target4>
    <UseTargetsInstreadOfPercentages>false</UseTargetsInstreadOfPercentages>
    <Symbol>STRAT</Symbol>
    <StartingAmount>4.995</StartingAmount>
    <CurrentAmount>0</CurrentAmount>
    <UsedTargets />
    <CurrentRateUSD>10.5641000000000000</CurrentRateUSD>
    <CurrentRateBTC>0</CurrentRateBTC>
    <MaxPercentageReached>23.34</MaxPercentageReached>
    <MaxBTCReached>0</MaxBTCReached>
    <TradeAtRateBTC>0.00074600</TradeAtRateBTC>
    <TradeAtRateUSD>10.5782800000000000</TradeAtRateUSD>
    <TradeAtDateTime>2017-12-22T00:15:34.6105376-06:00</TradeAtDateTime>
    <OrderID>4569004</OrderID>
    <OrderCompleted>true</OrderCompleted>
    <IsActive>false</IsActive>
    <IsParent>true</IsParent>
    <IsBuyObject>true</IsBuyObject>
    <LastAutoSellTime>0001-01-01T00:00:00</LastAutoSellTime>
    <SoldAllTime>2017-12-22T00:16:42.3175638-06:00</SoldAllTime>
  </CryptoObject>
  <CryptoObject>
    <ID>f4648cfe-198d-4488-85f5-f17618269eca</ID>
    <Exchange>Binance</Exchange>
    <SellType>ShortTerm</SellType>
    <Target1>0</Target1>
    <Target2>0</Target2>
    <Target3>0</Target3>
    <Target4>0</Target4>
    <UseTargetsInstreadOfPercentages>false</UseTargetsInstreadOfPercentages>
    <Symbol>STRAT</Symbol>
    <StartingAmount>4.995</StartingAmount>
    <CurrentAmount>0.005</CurrentAmount>
    <UsedTargets />
    <CurrentRateUSD>0</CurrentRateUSD>
    <CurrentRateBTC>0</CurrentRateBTC>
    <MaxPercentageReached>0</MaxPercentageReached>
    <MaxBTCReached>0</MaxBTCReached>
    <TradeAtRateBTC>0.00074200</TradeAtRateBTC>
    <TradeAtRateUSD>10.4157</TradeAtRateUSD>
    <TradeAtDateTime>2017-12-22T00:16:23.7924369-06:00</TradeAtDateTime>
    <OrderID>4569034</OrderID>
    <OrderCompleted>true</OrderCompleted>
    <IsActive>true</IsActive>
    <IsParent>false</IsParent>
    <IsBuyObject>false</IsBuyObject>
    <LastAutoSellTime>0001-01-01T00:00:00</LastAutoSellTime>
    <SoldAllTime>0001-01-01T00:00:00</SoldAllTime>
  </CryptoObject>
  <CryptoObject>
    <ID>3993550b-1677-471a-98c1-05690d5d22a2</ID>
    <Exchange>Bittrex</Exchange>
    <SellType>ShortTerm</SellType>
    <Target1>0</Target1>
    <Target2>0</Target2>
    <Target3>0</Target3>
    <Target4>0</Target4>
    <UseTargetsInstreadOfPercentages>false</UseTargetsInstreadOfPercentages>
    <Symbol>BLITZ</Symbol>
    <StartingAmount>50</StartingAmount>
    <CurrentAmount>0</CurrentAmount>
    <UsedTargets />
    <CurrentRateUSD>0</CurrentRateUSD>
    <CurrentRateBTC>0</CurrentRateBTC>
    <MaxPercentageReached>0</MaxPercentageReached>
    <MaxBTCReached>0</MaxBTCReached>
    <TradeAtRateBTC>0.0001800112</TradeAtRateBTC>
    <TradeAtRateUSD>2.0791293600</TradeAtRateUSD>
    <TradeAtDateTime>2017-12-22T08:53:00.4371574-06:00</TradeAtDateTime>
    <OrderID>e76ed781-31e9-4dc5-adc0-da1294d54e2e</OrderID>
    <OrderCompleted>true</OrderCompleted>
    <IsActive>true</IsActive>
    <IsParent>false</IsParent>
    <IsBuyObject>false</IsBuyObject>
    <LastAutoSellTime>0001-01-01T00:00:00</LastAutoSellTime>
    <SoldAllTime>0001-01-01T00:00:00</SoldAllTime>
  </CryptoObject>
  <CryptoObject>
    <ID>c56ec785-66d8-4967-80cb-69a96d31a66d</ID>
    <Exchange>Bittrex</Exchange>
    <SellType>ShortTerm</SellType>
    <Target1>0</Target1>
    <Target2>0</Target2>
    <Target3>0</Target3>
    <Target4>0</Target4>
    <UseTargetsInstreadOfPercentages>false</UseTargetsInstreadOfPercentages>
    <Symbol>AMP</Symbol>
    <StartingAmount>300</StartingAmount>
    <CurrentAmount>0</CurrentAmount>
    <UsedTargets />
    <CurrentRateUSD>0.6502860005161</CurrentRateUSD>
    <CurrentRateBTC>0</CurrentRateBTC>
    <MaxPercentageReached>47.93</MaxPercentageReached>
    <MaxBTCReached>0</MaxBTCReached>
    <TradeAtRateBTC>0.0000397699666666666666666667</TradeAtRateBTC>
    <TradeAtRateUSD>0.4922726474000000000000004126</TradeAtRateUSD>
    <TradeAtDateTime>2017-12-22T10:04:32.3195902-06:00</TradeAtDateTime>
    <OrderID>2e0badfa-b493-4da5-9449-1ef5f2966044</OrderID>
    <OrderCompleted>true</OrderCompleted>
    <IsActive>false</IsActive>
    <IsParent>true</IsParent>
    <IsBuyObject>true</IsBuyObject>
    <LastAutoSellTime>2017-12-24T11:57:31.5914358-06:00</LastAutoSellTime>
    <SoldAllTime>2017-12-24T11:57:42.6571583-06:00</SoldAllTime>
  </CryptoObject>
  <CryptoObject>
    <ID>92588a8b-b153-42dc-a825-a76b2300861e</ID>
    <Exchange>Bittrex</Exchange>
    <SellType>ShortTerm</SellType>
    <Target1>0</Target1>
    <Target2>0</Target2>
    <Target3>0</Target3>
    <Target4>0</Target4>
    <UseTargetsInstreadOfPercentages>false</UseTargetsInstreadOfPercentages>
    <Symbol>BURST</Symbol>
    <StartingAmount>5000</StartingAmount>
    <CurrentAmount>0</CurrentAmount>
    <UsedTargets />
    <CurrentRateUSD>0.0689554800000484</CurrentRateUSD>
    <CurrentRateBTC>0</CurrentRateBTC>
    <MaxPercentageReached>18.53</MaxPercentageReached>
    <MaxBTCReached>0</MaxBTCReached>
    <TradeAtRateBTC>0.00000475</TradeAtRateBTC>
    <TradeAtRateUSD>0.05937500</TradeAtRateUSD>
    <TradeAtDateTime>2017-12-22T11:11:08.2731755-06:00</TradeAtDateTime>
    <OrderID>24f6e7d2-9904-45cb-a026-0a453c498a65</OrderID>
    <OrderCompleted>true</OrderCompleted>
    <IsActive>false</IsActive>
    <IsParent>true</IsParent>
    <IsBuyObject>true</IsBuyObject>
    <LastAutoSellTime>0001-01-01T00:00:00</LastAutoSellTime>
    <SoldAllTime>2017-12-22T22:28:52.1215951-06:00</SoldAllTime>
  </CryptoObject>
  <CryptoObject>
    <ID>11cccc60-48ed-4fba-a940-c734277508ed</ID>
    <Exchange>Bittrex</Exchange>
    <SellType>ShortTerm</SellType>
    <Target1>0</Target1>
    <Target2>0</Target2>
    <Target3>0</Target3>
    <Target4>0</Target4>
    <UseTargetsInstreadOfPercentages>false</UseTargetsInstreadOfPercentages>
    <Symbol>POT</Symbol>
    <StartingAmount>1000</StartingAmount>
    <CurrentAmount>500</CurrentAmount>
    <UsedTargets />
    <CurrentRateUSD>0</CurrentRateUSD>
    <CurrentRateBTC>0</CurrentRateBTC>
    <MaxPercentageReached>0</MaxPercentageReached>
    <MaxBTCReached>0</MaxBTCReached>
    <TradeAtRateBTC>0.00002149</TradeAtRateBTC>
    <TradeAtRateUSD>0.2858</TradeAtRateUSD>
    <TradeAtDateTime>2017-12-22T14:23:07.689331-06:00</TradeAtDateTime>
    <OrderID>d3d77aef-3678-4285-ac36-39078a428c2a</OrderID>
    <OrderCompleted>true</OrderCompleted>
    <IsActive>true</IsActive>
    <IsParent>false</IsParent>
    <IsBuyObject>false</IsBuyObject>
    <LastAutoSellTime>0001-01-01T00:00:00</LastAutoSellTime>
    <SoldAllTime>0001-01-01T00:00:00</SoldAllTime>
  </CryptoObject>
  <CryptoObject>
    <ID>81a86045-561f-4e9f-9fa3-ce811d79785f</ID>
    <Exchange>Bittrex</Exchange>
    <SellType>ShortTerm</SellType>
    <Target1>0</Target1>
    <Target2>0</Target2>
    <Target3>0</Target3>
    <Target4>0</Target4>
    <UseTargetsInstreadOfPercentages>false</UseTargetsInstreadOfPercentages>
    <Symbol>EDG</Symbol>
    <StartingAmount>200</StartingAmount>
    <CurrentAmount>0</CurrentAmount>
    <UsedTargets />
    <CurrentRateUSD>0</CurrentRateUSD>
    <CurrentRateBTC>0</CurrentRateBTC>
    <MaxPercentageReached>0</MaxPercentageReached>
    <MaxBTCReached>0</MaxBTCReached>
    <TradeAtRateBTC>0.00010839995</TradeAtRateBTC>
    <TradeAtRateUSD>1.5296</TradeAtRateUSD>
    <TradeAtDateTime>2017-12-22T15:40:46.8787916-06:00</TradeAtDateTime>
    <OrderID>3e33f9cf-8211-41df-8b75-056c4eb06454</OrderID>
    <OrderCompleted>true</OrderCompleted>
    <IsActive>true</IsActive>
    <IsParent>false</IsParent>
    <IsBuyObject>false</IsBuyObject>
    <LastAutoSellTime>0001-01-01T00:00:00</LastAutoSellTime>
    <SoldAllTime>0001-01-01T00:00:00</SoldAllTime>
  </CryptoObject>
  <CryptoObject>
    <ID>11cccc60-48ed-4fba-a940-c734277508ed</ID>
    <Exchange>Bittrex</Exchange>
    <SellType>ShortTerm</SellType>
    <Target1>0</Target1>
    <Target2>0</Target2>
    <Target3>0</Target3>
    <Target4>0</Target4>
    <UseTargetsInstreadOfPercentages>false</UseTargetsInstreadOfPercentages>
    <Symbol>POT</Symbol>
    <StartingAmount>500</StartingAmount>
    <CurrentAmount>0</CurrentAmount>
    <UsedTargets />
    <CurrentRateUSD>0</CurrentRateUSD>
    <CurrentRateBTC>0</CurrentRateBTC>
    <MaxPercentageReached>0</MaxPercentageReached>
    <MaxBTCReached>0</MaxBTCReached>
    <TradeAtRateBTC>0.00002101</TradeAtRateBTC>
    <TradeAtRateUSD>0.2933</TradeAtRateUSD>
    <TradeAtDateTime>2017-12-22T16:23:00.7877364-06:00</TradeAtDateTime>
    <OrderID>fcc83543-e4e1-4bb3-8aed-8636d69ca0c4</OrderID>
    <OrderCompleted>true</OrderCompleted>
    <IsActive>true</IsActive>
    <IsParent>false</IsParent>
    <IsBuyObject>false</IsBuyObject>
    <LastAutoSellTime>0001-01-01T00:00:00</LastAutoSellTime>
    <SoldAllTime>0001-01-01T00:00:00</SoldAllTime>
  </CryptoObject>
  <CryptoObject>
    <ID>fff635ff-7dd0-4872-ae23-8179f8ba5b3c</ID>
    <Exchange>Bittrex</Exchange>
    <SellType>ShortTerm</SellType>
    <Target1>0</Target1>
    <Target2>0</Target2>
    <Target3>0</Target3>
    <Target4>0</Target4>
    <UseTargetsInstreadOfPercentages>false</UseTargetsInstreadOfPercentages>
    <Symbol>SC</Symbol>
    <StartingAmount>20000</StartingAmount>
    <CurrentAmount>0</CurrentAmount>
    <UsedTargets />
    <CurrentRateUSD>0.02318400</CurrentRateUSD>
    <CurrentRateBTC>0</CurrentRateBTC>
    <MaxPercentageReached>16.10</MaxPercentageReached>
    <MaxBTCReached>0</MaxBTCReached>
    <TradeAtRateBTC>0.00000145</TradeAtRateBTC>
    <TradeAtRateUSD>0.0193994050533455</TradeAtRateUSD>
    <TradeAtDateTime>2017-12-22T19:05:03.8419814-06:00</TradeAtDateTime>
    <OrderID>9679abf6-3ed3-4ad9-9029-589f52e4d391</OrderID>
    <OrderCompleted>true</OrderCompleted>
    <IsActive>false</IsActive>
    <IsParent>true</IsParent>
    <IsBuyObject>true</IsBuyObject>
    <LastAutoSellTime>0001-01-01T00:00:00</LastAutoSellTime>
    <SoldAllTime>2017-12-23T06:56:05.4634293-06:00</SoldAllTime>
  </CryptoObject>
  <CryptoObject>
    <ID>92588a8b-b153-42dc-a825-a76b2300861e</ID>
    <Exchange>Bittrex</Exchange>
    <SellType>ShortTerm</SellType>
    <Target1>0</Target1>
    <Target2>0</Target2>
    <Target3>0</Target3>
    <Target4>0</Target4>
    <UseTargetsInstreadOfPercentages>false</UseTargetsInstreadOfPercentages>
    <Symbol>BURST</Symbol>
    <StartingAmount>5000</StartingAmount>
    <CurrentAmount>0</CurrentAmount>
    <UsedTargets />
    <CurrentRateUSD>0</CurrentRateUSD>
    <CurrentRateBTC>0</CurrentRateBTC>
    <MaxPercentageReached>0</MaxPercentageReached>
    <MaxBTCReached>0</MaxBTCReached>
    <TradeAtRateBTC>0.00000481</TradeAtRateBTC>
    <TradeAtRateUSD>0.0685</TradeAtRateUSD>
    <TradeAtDateTime>2017-12-22T22:28:52.1205944-06:00</TradeAtDateTime>
    <OrderID>f1c821b9-19ea-4a62-9099-1d3e4bb4f6d9</OrderID>
    <OrderCompleted>true</OrderCompleted>
    <IsActive>true</IsActive>
    <IsParent>false</IsParent>
    <IsBuyObject>false</IsBuyObject>
    <LastAutoSellTime>0001-01-01T00:00:00</LastAutoSellTime>
    <SoldAllTime>0001-01-01T00:00:00</SoldAllTime>
  </CryptoObject>
  <CryptoObject>
    <ID>fff635ff-7dd0-4872-ae23-8179f8ba5b3c</ID>
    <Exchange>Bittrex</Exchange>
    <SellType>ShortTerm</SellType>
    <Target1>0</Target1>
    <Target2>0</Target2>
    <Target3>0</Target3>
    <Target4>0</Target4>
    <UseTargetsInstreadOfPercentages>false</UseTargetsInstreadOfPercentages>
    <Symbol>SC</Symbol>
    <StartingAmount>20000</StartingAmount>
    <CurrentAmount>0</CurrentAmount>
    <UsedTargets />
    <CurrentRateUSD>0</CurrentRateUSD>
    <CurrentRateBTC>0</CurrentRateBTC>
    <MaxPercentageReached>0</MaxPercentageReached>
    <MaxBTCReached>0</MaxBTCReached>
    <TradeAtRateBTC>0.00000161</TradeAtRateBTC>
    <TradeAtRateUSD>0.0232</TradeAtRateUSD>
    <TradeAtDateTime>2017-12-23T06:56:05.461421-06:00</TradeAtDateTime>
    <OrderID>6d4cc08f-0796-4c4a-b847-495d58177f4c</OrderID>
    <OrderCompleted>true</OrderCompleted>
    <IsActive>true</IsActive>
    <IsParent>false</IsParent>
    <IsBuyObject>false</IsBuyObject>
    <LastAutoSellTime>0001-01-01T00:00:00</LastAutoSellTime>
    <SoldAllTime>0001-01-01T00:00:00</SoldAllTime>
  </CryptoObject>
  <CryptoObject>
    <ID>b3fc75b8-c70c-408b-bebd-6d39225c9a5e</ID>
    <Exchange>Bittrex</Exchange>
    <SellType>ShortTerm</SellType>
    <Target1>0</Target1>
    <Target2>0</Target2>
    <Target3>0</Target3>
    <Target4>0</Target4>
    <UseTargetsInstreadOfPercentages>false</UseTargetsInstreadOfPercentages>
    <Symbol>VTC</Symbol>
    <StartingAmount>20</StartingAmount>
    <CurrentAmount>20</CurrentAmount>
    <UsedTargets />
    <CurrentRateUSD>7.25641490</CurrentRateUSD>
    <CurrentRateBTC>0.00047771</CurrentRateBTC>
    <MaxPercentageReached>16.05</MaxPercentageReached>
    <MaxBTCReached>0.00049958</MaxBTCReached>
    <TradeAtRateBTC>0.00051</TradeAtRateBTC>
    <TradeAtRateUSD>7.34400</TradeAtRateUSD>
    <TradeAtDateTime>2017-12-23T07:00:40.9458247-06:00</TradeAtDateTime>
    <OrderID>7665fe8e-c471-44d0-9864-a17f7b6780c2</OrderID>
    <OrderCompleted>true</OrderCompleted>
    <IsActive>true</IsActive>
    <IsParent>true</IsParent>
    <IsBuyObject>true</IsBuyObject>
    <LastAutoSellTime>0001-01-01T00:00:00</LastAutoSellTime>
    <SoldAllTime>0001-01-01T00:00:00</SoldAllTime>
  </CryptoObject>
  <CryptoObject>
    <ID>3aad3f63-29ae-4609-96fb-764a49541620</ID>
    <Exchange>Bittrex</Exchange>
    <SellType>ShortTerm</SellType>
    <Target1>0</Target1>
    <Target2>0</Target2>
    <Target3>0</Target3>
    <Target4>0</Target4>
    <UseTargetsInstreadOfPercentages>false</UseTargetsInstreadOfPercentages>
    <Symbol>XEM</Symbol>
    <StartingAmount>200</StartingAmount>
    <CurrentAmount>200</CurrentAmount>
    <UsedTargets />
    <CurrentRateUSD>0.94799250</CurrentRateUSD>
    <CurrentRateBTC>0.00006019</CurrentRateBTC>
    <MaxPercentageReached>20.14</MaxPercentageReached>
    <MaxBTCReached>0.00007835</MaxBTCReached>
    <TradeAtRateBTC>0.00006200998</TradeAtRateBTC>
    <TradeAtRateUSD>0.89294371200</TradeAtRateUSD>
    <TradeAtDateTime>2017-12-23T07:00:42.9485556-06:00</TradeAtDateTime>
    <OrderID>acb88cc8-a123-4646-a1f0-b3f482434475</OrderID>
    <OrderCompleted>true</OrderCompleted>
    <IsActive>false</IsActive>
    <IsParent>true</IsParent>
    <IsBuyObject>true</IsBuyObject>
    <LastAutoSellTime>0001-01-01T00:00:00</LastAutoSellTime>
    <SoldAllTime>2017-12-26T07:00:42.9485556-06:00</SoldAllTime>
  </CryptoObject>
  <CryptoObject>
    <ID>3aad3f63-29ae-4609-96fb-764a49541620</ID>
    <Exchange>Bittrex</Exchange>
    <SellType>ShortTerm</SellType>
    <Target1>0</Target1>
    <Target2>0</Target2>
    <Target3>0</Target3>
    <Target4>0</Target4>
    <UseTargetsInstreadOfPercentages>false</UseTargetsInstreadOfPercentages>
    <Symbol>XEM</Symbol>
    <StartingAmount>200</StartingAmount>
    <CurrentAmount>50</CurrentAmount>
    <UsedTargets />
    <CurrentRateUSD>0.94799250</CurrentRateUSD>
    <CurrentRateBTC>0.00006019</CurrentRateBTC>
    <MaxPercentageReached>18.74</MaxPercentageReached>
    <MaxBTCReached>0.00006019</MaxBTCReached>
    <TradeAtRateBTC>0.00007450</TradeAtRateBTC>
    <TradeAtRateUSD>0.89294371200</TradeAtRateUSD>
    <TradeAtDateTime>2017-12-24T07:00:42.9485556-06:00</TradeAtDateTime>
    <OrderID>acb88cdc8-a123-4646-a1f0-b3f482434475</OrderID>
    <OrderCompleted>true</OrderCompleted>
    <IsActive>false</IsActive>
    <IsParent>false</IsParent>
    <IsBuyObject>false</IsBuyObject>
    <LastAutoSellTime>0001-01-01T00:00:00</LastAutoSellTime>
    <SoldAllTime>0001-01-01T00:00:00</SoldAllTime>
  </CryptoObject>
  <CryptoObject>
    <ID>3aad3f63-29ae-4609-96fb-764a49541620</ID>
    <Exchange>Bittrex</Exchange>
    <SellType>ShortTerm</SellType>
    <Target1>0</Target1>
    <Target2>0</Target2>
    <Target3>0</Target3>
    <Target4>0</Target4>
    <UseTargetsInstreadOfPercentages>false</UseTargetsInstreadOfPercentages>
    <Symbol>XEM</Symbol>
    <StartingAmount>50</StartingAmount>
    <CurrentAmount>0</CurrentAmount>
    <UsedTargets />
    <CurrentRateUSD>0.94799250</CurrentRateUSD>
    <CurrentRateBTC>0.00007835</CurrentRateBTC>
    <MaxPercentageReached>18.74</MaxPercentageReached>
    <MaxBTCReached>0.00006019</MaxBTCReached>
    <TradeAtRateBTC>0.00007450</TradeAtRateBTC>
    <TradeAtRateUSD>0.89294371200</TradeAtRateUSD>
    <TradeAtDateTime>2017-12-24T07:00:42.9485556-06:00</TradeAtDateTime>
    <OrderID>aceb88cdc8-a123-4646-a1f0-b3f482434475</OrderID>
    <OrderCompleted>true</OrderCompleted>
    <IsActive>false</IsActive>
    <IsParent>false</IsParent>
    <IsBuyObject>false</IsBuyObject>
    <LastAutoSellTime>0001-01-01T00:00:00</LastAutoSellTime>
    <SoldAllTime>0001-01-01T00:00:00</SoldAllTime>
  </CryptoObject>
  <CryptoObject>
    <ID>fa1e7276-0200-421f-9ccc-7f640823b51f</ID>
    <Exchange>Bittrex</Exchange>
    <SellType>ShortTerm</SellType>
    <Target1>0</Target1>
    <Target2>0</Target2>
    <Target3>0</Target3>
    <Target4>0</Target4>
    <UseTargetsInstreadOfPercentages>false</UseTargetsInstreadOfPercentages>
    <Symbol>XLM</Symbol>
    <StartingAmount>800</StartingAmount>
    <CurrentAmount>800</CurrentAmount>
    <UsedTargets />
    <CurrentRateUSD>0.22724240</CurrentRateUSD>
    <CurrentRateBTC>0.00001496</CurrentRateBTC>
    <MaxPercentageReached>11.05</MaxPercentageReached>
    <MaxBTCReached>0.00001507</MaxBTCReached>
    <TradeAtRateBTC>0.0000158</TradeAtRateBTC>
    <TradeAtRateUSD>0.228688164957010</TradeAtRateUSD>
    <TradeAtDateTime>2017-12-23T07:03:29.4552676-06:00</TradeAtDateTime>
    <OrderID>52a536f0-8590-4631-b4b1-975bff89dea5</OrderID>
    <OrderCompleted>true</OrderCompleted>
    <IsActive>true</IsActive>
    <IsParent>true</IsParent>
    <IsBuyObject>true</IsBuyObject>
    <LastAutoSellTime>0001-01-01T00:00:00</LastAutoSellTime>
    <SoldAllTime>0001-01-01T00:00:00</SoldAllTime>
  </CryptoObject>
  <CryptoObject>
    <ID>b20f41de-ca7c-47d2-890e-9a18f49366d0</ID>
    <Exchange>Bittrex</Exchange>
    <SellType>ShortTerm</SellType>
    <Target1>0</Target1>
    <Target2>0</Target2>
    <Target3>0</Target3>
    <Target4>0</Target4>
    <UseTargetsInstreadOfPercentages>false</UseTargetsInstreadOfPercentages>
    <Symbol>SALT</Symbol>
    <StartingAmount>50</StartingAmount>
    <CurrentAmount>0</CurrentAmount>
    <UsedTargets>,Short_Target1</UsedTargets>
    <CurrentRateUSD>13.560750</CurrentRateUSD>
    <CurrentRateBTC>0.000861</CurrentRateBTC>
    <MaxPercentageReached>23.90</MaxPercentageReached>
    <MaxBTCReached>0.000861</MaxBTCReached>
    <TradeAtRateBTC>0.0006956498</TradeAtRateBTC>
    <TradeAtRateUSD>10.0695308550</TradeAtRateUSD>
    <TradeAtDateTime>2017-12-23T07:38:43.288694-06:00</TradeAtDateTime>
    <OrderID>c0832247-946f-40eb-bd34-128aedfc7e07</OrderID>
    <OrderCompleted>true</OrderCompleted>
    <IsActive>false</IsActive>
    <IsParent>true</IsParent>
    <IsBuyObject>true</IsBuyObject>
    <LastAutoSellTime>2017-12-27T07:57:34.4653094-06:00</LastAutoSellTime>
    <SoldAllTime>2017-12-27T07:38:43.288694-06:00</SoldAllTime>
  </CryptoObject>
  <CryptoObject>
    <ID>b20f41de-ca7c-47d2-890e-9a18f49366d0</ID>
    <Exchange>Bittrex</Exchange>
    <SellType>ShortTerm</SellType>
    <Target1>0</Target1>
    <Target2>0</Target2>
    <Target3>0</Target3>
    <Target4>0</Target4>
    <UseTargetsInstreadOfPercentages>false</UseTargetsInstreadOfPercentages>
    <Symbol>SALT</Symbol>
    <StartingAmount>50</StartingAmount>
    <CurrentAmount>35</CurrentAmount>
    <UsedTargets />
    <CurrentRateUSD>0.517120490001907</CurrentRateUSD>
    <CurrentRateBTC>0</CurrentRateBTC>
    <MaxPercentageReached>12.91</MaxPercentageReached>
    <MaxBTCReached>0</MaxBTCReached>
    <TradeAtRateBTC>0.00083600</TradeAtRateBTC>
    <TradeAtRateUSD>0.47415253</TradeAtRateUSD>
    <TradeAtDateTime>2017-12-23T22:52:17.8334986-06:00</TradeAtDateTime>
    <OrderID>4c814ee9-689c-4d94-9751-5c4375511316</OrderID>
    <OrderCompleted>true</OrderCompleted>
    <IsActive>false</IsActive>
    <IsParent>false</IsParent>
    <IsBuyObject>false</IsBuyObject>
    <LastAutoSellTime>0001-01-01T00:00:00</LastAutoSellTime>
    <SoldAllTime>2017-12-24T09:18:37.4697797-06:00</SoldAllTime>
  </CryptoObject>
  <CryptoObject>
    <ID>b20f41de-ca7c-47d2-890e-9a18f49366d0</ID>
    <Exchange>Bittrex</Exchange>
    <SellType>ShortTerm</SellType>
    <Target1>0</Target1>
    <Target2>0</Target2>
    <Target3>0</Target3>
    <Target4>0</Target4>
    <UseTargetsInstreadOfPercentages>false</UseTargetsInstreadOfPercentages>
    <Symbol>SALT</Symbol>
    <StartingAmount>35</StartingAmount>
    <CurrentAmount>20</CurrentAmount>
    <UsedTargets />
    <CurrentRateUSD>0.517120490001907</CurrentRateUSD>
    <CurrentRateBTC>0</CurrentRateBTC>
    <MaxPercentageReached>12.91</MaxPercentageReached>
    <MaxBTCReached>0</MaxBTCReached>
    <TradeAtRateBTC>0.00084447</TradeAtRateBTC>
    <TradeAtRateUSD>0.47415253</TradeAtRateUSD>
    <TradeAtDateTime>2017-12-23T22:52:17.8334986-06:00</TradeAtDateTime>
    <OrderID>4c814ee9-679c-4d94-9751-5c4375511316</OrderID>
    <OrderCompleted>true</OrderCompleted>
    <IsActive>false</IsActive>
    <IsParent>false</IsParent>
    <IsBuyObject>false</IsBuyObject>
    <LastAutoSellTime>0001-01-01T00:00:00</LastAutoSellTime>
    <SoldAllTime>2017-12-24T09:18:37.4697797-06:00</SoldAllTime>
  </CryptoObject>
  <CryptoObject>
    <ID>b20f41de-ca7c-47d2-890e-9a18f49366d0</ID>
    <Exchange>Bittrex</Exchange>
    <SellType>ShortTerm</SellType>
    <Target1>0</Target1>
    <Target2>0</Target2>
    <Target3>0</Target3>
    <Target4>0</Target4>
    <UseTargetsInstreadOfPercentages>false</UseTargetsInstreadOfPercentages>
    <Symbol>SALT</Symbol>
    <StartingAmount>20</StartingAmount>
    <CurrentAmount>5</CurrentAmount>
    <UsedTargets />
    <CurrentRateUSD>0.517120490001907</CurrentRateUSD>
    <CurrentRateBTC>0</CurrentRateBTC>
    <MaxPercentageReached>12.91</MaxPercentageReached>
    <MaxBTCReached>0</MaxBTCReached>
    <TradeAtRateBTC>0.00084002</TradeAtRateBTC>
    <TradeAtRateUSD>0.47415253</TradeAtRateUSD>
    <TradeAtDateTime>2017-12-23T22:52:17.8334986-06:00</TradeAtDateTime>
    <OrderID>4c914ee9-679c-4d94-9751-5c4375511316</OrderID>
    <OrderCompleted>true</OrderCompleted>
    <IsActive>false</IsActive>
    <IsParent>false</IsParent>
    <IsBuyObject>false</IsBuyObject>
    <LastAutoSellTime>0001-01-01T00:00:00</LastAutoSellTime>
    <SoldAllTime>2017-12-24T09:18:37.4697797-06:00</SoldAllTime>
  </CryptoObject>
  <CryptoObject>
    <ID>b20f41de-ca7c-47d2-890e-9a18f49366d0</ID>
    <Exchange>Bittrex</Exchange>
    <SellType>ShortTerm</SellType>
    <Target1>0</Target1>
    <Target2>0</Target2>
    <Target3>0</Target3>
    <Target4>0</Target4>
    <UseTargetsInstreadOfPercentages>false</UseTargetsInstreadOfPercentages>
    <Symbol>SALT</Symbol>
    <StartingAmount>5</StartingAmount>
    <CurrentAmount>0</CurrentAmount>
    <UsedTargets />
    <CurrentRateUSD>0.517120490001907</CurrentRateUSD>
    <CurrentRateBTC>0</CurrentRateBTC>
    <MaxPercentageReached>12.91</MaxPercentageReached>
    <MaxBTCReached>0</MaxBTCReached>
    <TradeAtRateBTC>0.00083335</TradeAtRateBTC>
    <TradeAtRateUSD>0.47415253</TradeAtRateUSD>
    <TradeAtDateTime>2017-12-23T22:52:17.8334986-06:00</TradeAtDateTime>
    <OrderID>42914ee9-679c-4d94-9751-5c4375511316</OrderID>
    <OrderCompleted>true</OrderCompleted>
    <IsActive>false</IsActive>
    <IsParent>false</IsParent>
    <IsBuyObject>false</IsBuyObject>
    <LastAutoSellTime>0001-01-01T00:00:00</LastAutoSellTime>
    <SoldAllTime>2017-12-25T09:18:37.4697797-06:00</SoldAllTime>
  </CryptoObject>
  <CryptoObject>
    <ID>542d58a0-62ae-4be0-96c9-965a9f52093a</ID>
    <Exchange>Bittrex</Exchange>
    <SellType>ShortTerm</SellType>
    <Target1>0</Target1>
    <Target2>0</Target2>
    <Target3>0</Target3>
    <Target4>0</Target4>
    <UseTargetsInstreadOfPercentages>false</UseTargetsInstreadOfPercentages>
    <Symbol>AUR</Symbol>
    <StartingAmount>100</StartingAmount>
    <CurrentAmount>100</CurrentAmount>
    <UsedTargets />
    <CurrentRateUSD>1.458240</CurrentRateUSD>
    <CurrentRateBTC>0.000096</CurrentRateBTC>
    <MaxPercentageReached>4.38</MaxPercentageReached>
    <MaxBTCReached>0.00009876</MaxBTCReached>
    <TradeAtRateBTC>0.00009707</TradeAtRateBTC>
    <TradeAtRateUSD>12.8010243000000000</TradeAtRateUSD>
    <TradeAtDateTime>2017-12-23T16:14:48.7037685-06:00</TradeAtDateTime>
    <OrderID>4542085</OrderID>
    <OrderCompleted>true</OrderCompleted>
    <IsActive>true</IsActive>
    <IsParent>true</IsParent>
    <IsBuyObject>true</IsBuyObject>
    <LastAutoSellTime>0001-01-01T00:00:00</LastAutoSellTime>
    <SoldAllTime>0001-01-01T00:00:00</SoldAllTime>
  </CryptoObject>
  <CryptoObject>
    <ID>a6e9f4d1-fea9-473d-9384-76091deee94b</ID>
    <Exchange>Binance</Exchange>
    <SellType>ShortTerm</SellType>
    <Target1>0</Target1>
    <Target2>0</Target2>
    <Target3>0</Target3>
    <Target4>0</Target4>
    <UseTargetsInstreadOfPercentages>false</UseTargetsInstreadOfPercentages>
    <Symbol>LEND</Symbol>
    <StartingAmount>4995.00000000</StartingAmount>
    <CurrentAmount>0.00000000</CurrentAmount>
    <UsedTargets />
    <CurrentRateUSD>0</CurrentRateUSD>
    <CurrentRateBTC>0</CurrentRateBTC>
    <MaxPercentageReached>0</MaxPercentageReached>
    <MaxBTCReached>0</MaxBTCReached>
    <TradeAtRateBTC>0.00000446</TradeAtRateBTC>
    <TradeAtRateUSD>0.0591396000000000</TradeAtRateUSD>
    <TradeAtDateTime>2017-12-23T21:55:05.203026-06:00</TradeAtDateTime>
    <OrderID>817675</OrderID>
    <OrderCompleted>true</OrderCompleted>
    <IsActive>true</IsActive>
    <IsParent>false</IsParent>
    <IsBuyObject>false</IsBuyObject>
    <LastAutoSellTime>0001-01-01T00:00:00</LastAutoSellTime>
    <SoldAllTime>0001-01-01T00:00:00</SoldAllTime>
  </CryptoObject>
  <CryptoObject>
    <ID>c56ec785-66d8-4967-80cb-69a96d31a66d</ID>
    <Exchange>Bittrex</Exchange>
    <SellType>ShortTerm</SellType>
    <Target1>0</Target1>
    <Target2>0</Target2>
    <Target3>0</Target3>
    <Target4>0</Target4>
    <UseTargetsInstreadOfPercentages>false</UseTargetsInstreadOfPercentages>
    <Symbol>AMP</Symbol>
    <StartingAmount>300</StartingAmount>
    <CurrentAmount>195</CurrentAmount>
    <UsedTargets />
    <CurrentRateUSD>0</CurrentRateUSD>
    <CurrentRateBTC>0</CurrentRateBTC>
    <MaxPercentageReached>0</MaxPercentageReached>
    <MaxBTCReached>0</MaxBTCReached>
    <TradeAtRateBTC>0.00004817</TradeAtRateBTC>
    <TradeAtRateUSD>0.6474</TradeAtRateUSD>
    <TradeAtDateTime>2017-12-23T21:56:34.4370452-06:00</TradeAtDateTime>
    <OrderID>4849b7bd-3b34-4611-9f69-3b733267ab04</OrderID>
    <OrderCompleted>true</OrderCompleted>
    <IsActive>true</IsActive>
    <IsParent>false</IsParent>
    <IsBuyObject>false</IsBuyObject>
    <LastAutoSellTime>0001-01-01T00:00:00</LastAutoSellTime>
    <SoldAllTime>0001-01-01T00:00:00</SoldAllTime>
  </CryptoObject>
  <CryptoObject>
    <ID>4ddf203e-508f-4fd2-9a5c-ddc45cfbd9b9</ID>
    <Exchange>Bittrex</Exchange>
    <SellType>ShortTerm</SellType>
    <Target1>0</Target1>
    <Target2>0</Target2>
    <Target3>0</Target3>
    <Target4>0</Target4>
    <UseTargetsInstreadOfPercentages>false</UseTargetsInstreadOfPercentages>
    <Symbol>CURE</Symbol>
    <StartingAmount>200</StartingAmount>
    <CurrentAmount>0</CurrentAmount>
    <UsedTargets />
    <CurrentRateUSD>0.517120490001907</CurrentRateUSD>
    <CurrentRateBTC>0</CurrentRateBTC>
    <MaxPercentageReached>12.91</MaxPercentageReached>
    <MaxBTCReached>0</MaxBTCReached>
    <TradeAtRateBTC>0.00003617</TradeAtRateBTC>
    <TradeAtRateUSD>0.47415253</TradeAtRateUSD>
    <TradeAtDateTime>2017-12-23T22:52:17.8334986-06:00</TradeAtDateTime>
    <OrderID>4c814ee9-689c-4d94-9751-5c4375519316</OrderID>
    <OrderCompleted>true</OrderCompleted>
    <IsActive>false</IsActive>
    <IsParent>true</IsParent>
    <IsBuyObject>true</IsBuyObject>
    <LastAutoSellTime>0001-01-01T00:00:00</LastAutoSellTime>
    <SoldAllTime>2017-12-24T08:18:37.4697797-06:00</SoldAllTime>
  </CryptoObject>
  <CryptoObject>
    <ID>c56ec785-66d8-4967-80cb-69a96d31a66d</ID>
    <Exchange>Bittrex</Exchange>
    <SellType>ShortTerm</SellType>
    <Target1>0</Target1>
    <Target2>0</Target2>
    <Target3>0</Target3>
    <Target4>0</Target4>
    <UseTargetsInstreadOfPercentages>false</UseTargetsInstreadOfPercentages>
    <Symbol>AMP</Symbol>
    <StartingAmount>195</StartingAmount>
    <CurrentAmount>90</CurrentAmount>
    <UsedTargets />
    <CurrentRateUSD>0</CurrentRateUSD>
    <CurrentRateBTC>0</CurrentRateBTC>
    <MaxPercentageReached>0</MaxPercentageReached>
    <MaxBTCReached>0</MaxBTCReached>
    <TradeAtRateBTC>0.00004735</TradeAtRateBTC>
    <TradeAtRateUSD>0.6264</TradeAtRateUSD>
    <TradeAtDateTime>2017-12-23T22:59:48.8123105-06:00</TradeAtDateTime>
    <OrderID>4506657d-0784-4ebd-8189-8cf06ae67de0</OrderID>
    <OrderCompleted>true</OrderCompleted>
    <IsActive>true</IsActive>
    <IsParent>false</IsParent>
    <IsBuyObject>false</IsBuyObject>
    <LastAutoSellTime>0001-01-01T00:00:00</LastAutoSellTime>
    <SoldAllTime>0001-01-01T00:00:00</SoldAllTime>
  </CryptoObject>
  <CryptoObject>
    <ID>d1bdfbb6-b14e-41bb-9939-3c2b7ab40e40</ID>
    <Exchange>Bittrex</Exchange>
    <SellType>ShortTerm</SellType>
    <Target1>0</Target1>
    <Target2>0</Target2>
    <Target3>0</Target3>
    <Target4>0</Target4>
    <UseTargetsInstreadOfPercentages>true</UseTargetsInstreadOfPercentages>
    <SellAllAtTarget />
    <SellAllAtTargetAndAfterReaching>,</SellAllAtTargetAndAfterReaching>
    <Symbol>ADA</Symbol>
    <StartingAmount>37</StartingAmount>
    <CurrentAmount>37</CurrentAmount>
    <UsedTargets />
    <CurrentRateUSD>0.40921860</CurrentRateUSD>
    <CurrentRateBTC>0.00002694</CurrentRateBTC>
    <MaxPercentageReached>5.97</MaxPercentageReached>
    <MaxBTCReached>0.00002748</MaxBTCReached>
    <TradeAtRateBTC>0.00002743</TradeAtRateBTC>
    <TradeAtRateUSD>0.36758943</TradeAtRateUSD>
    <TradeAtDateTime>2017-12-24T00:25:53.8888816-06:00</TradeAtDateTime>
    <OrderID>08591582-644d-485a-b7e3-866e537a6d32</OrderID>
    <OrderCompleted>true</OrderCompleted>
    <IsActive>true</IsActive>
    <IsParent>true</IsParent>
    <IsBuyObject>true</IsBuyObject>
    <LastAutoSellTime>0001-01-01T00:00:00</LastAutoSellTime>
    <SoldAllTime>0001-01-01T00:00:00</SoldAllTime>
  </CryptoObject>
  <CryptoObject>
    <ID>7df80b2c-8379-4c63-a3a1-5fc89b04e71d</ID>
    <Exchange>Binance</Exchange>
    <SellType>ShortTerm</SellType>
    <Target1>0</Target1>
    <Target2>0</Target2>
    <Target3>0</Target3>
    <Target4>0</Target4>
    <UseTargetsInstreadOfPercentages>false</UseTargetsInstreadOfPercentages>
    <Symbol>IOTA</Symbol>
    <StartingAmount>99.9</StartingAmount>
    <CurrentAmount>99.9</CurrentAmount>
    <UsedTargets />
    <CurrentRateUSD>3.8040382464000000</CurrentRateUSD>
    <CurrentRateBTC>0.00025088</CurrentRateBTC>
    <MaxPercentageReached>2.24</MaxPercentageReached>
    <MaxBTCReached>0.00025991</MaxBTCReached>
    <TradeAtRateBTC>0.00025822</TradeAtRateBTC>
    <TradeAtRateUSD>3.2126183080000000</TradeAtRateUSD>
    <TradeAtDateTime>2017-12-24T07:19:32.61159-06:00</TradeAtDateTime>
    <OrderID>10213742</OrderID>
    <OrderCompleted>true</OrderCompleted>
    <IsActive>true</IsActive>
    <IsParent>true</IsParent>
    <IsBuyObject>true</IsBuyObject>
    <LastAutoSellTime>0001-01-01T00:00:00</LastAutoSellTime>
    <SoldAllTime>0001-01-01T00:00:00</SoldAllTime>
  </CryptoObject>
  <CryptoObject>
    <ID>1e237d9f-0f83-4ab4-a03d-3245bbda2ea6</ID>
    <Exchange>Binance</Exchange>
    <SellType>MidTerm</SellType>
    <Target1>0.0006359</Target1>
    <Target2>0.0008359</Target2>
    <Target3>0.0010359</Target3>
    <Target4>0</Target4>
    <UseTargetsInstreadOfPercentages>true</UseTargetsInstreadOfPercentages>
    <SellAllAtTarget>Target 3</SellAllAtTarget>
    <SellAllAtTargetAndAfterReaching>Target 2,Target 3</SellAllAtTargetAndAfterReaching>
    <Symbol>EOS</Symbol>
    <StartingAmount>24.975</StartingAmount>
    <CurrentAmount>24.975</CurrentAmount>
    <UsedTargets />
    <CurrentRateUSD>8.5683353502000000</CurrentRateUSD>
    <CurrentRateBTC>0.00056509</CurrentRateBTC>
    <MaxPercentageReached>1.02</MaxPercentageReached>
    <MaxBTCReached>0.00058211</MaxBTCReached>
    <TradeAtRateBTC>0.00059483</TradeAtRateBTC>
    <TradeAtRateUSD>7.5246113966000000</TradeAtRateUSD>
    <TradeAtDateTime>2017-12-24T07:23:31.4027205-06:00</TradeAtDateTime>
    <OrderID>7437870</OrderID>
    <OrderCompleted>true</OrderCompleted>
    <IsActive>true</IsActive>
    <IsParent>true</IsParent>
    <IsBuyObject>true</IsBuyObject>
    <LastAutoSellTime>0001-01-01T00:00:00</LastAutoSellTime>
    <SoldAllTime>0001-01-01T00:00:00</SoldAllTime>
  </CryptoObject>
  <CryptoObject>
    <ID>a1fb5f1a-a140-45cb-9653-d1b98b847b7e</ID>
    <Exchange>Bittrex</Exchange>
    <SellType>MidTerm</SellType>
    <Target1>0.00451208</Target1>
    <Target2>0.00531208</Target2>
    <Target3>0.00731208</Target3>
    <Target4>0</Target4>
    <UseTargetsInstreadOfPercentages>true</UseTargetsInstreadOfPercentages>
    <SellAllAtTarget>Target 3</SellAllAtTarget>
    <SellAllAtTargetAndAfterReaching>Target 2,Target 3</SellAllAtTargetAndAfterReaching>
    <Symbol>NEO</Symbol>
    <StartingAmount>10</StartingAmount>
    <CurrentAmount>10</CurrentAmount>
    <UsedTargets />
    <CurrentRateUSD>65.42226670</CurrentRateUSD>
    <CurrentRateBTC>0.00430693</CurrentRateBTC>
    <MaxPercentageReached>6.37</MaxPercentageReached>
    <MaxBTCReached>0.00437116</MaxBTCReached>
    <TradeAtRateBTC>0.004159</TradeAtRateBTC>
    <TradeAtRateUSD>51.57575900020795</TradeAtRateUSD>
    <TradeAtDateTime>2017-12-24T07:47:35.8105244-06:00</TradeAtDateTime>
    <OrderID>5ddf3359-3382-4c79-a282-863f693cd091</OrderID>
    <OrderCompleted>true</OrderCompleted>
    <IsActive>true</IsActive>
    <IsParent>true</IsParent>
    <IsBuyObject>true</IsBuyObject>
    <LastAutoSellTime>0001-01-01T00:00:00</LastAutoSellTime>
    <SoldAllTime>0001-01-01T00:00:00</SoldAllTime>
  </CryptoObject>
  <CryptoObject>
    <ID>2d97d804-4557-4243-bf61-d842553c91a7</ID>
    <Exchange>Bittrex</Exchange>
    <SellType>ShortTerm</SellType>
    <Target1>0.00112000</Target1>
    <Target2>0.00122000</Target2>
    <Target3>0.00142000</Target3>
    <Target4>0</Target4>
    <UseTargetsInstreadOfPercentages>true</UseTargetsInstreadOfPercentages>
    <SellAllAtTarget>Target 3</SellAllAtTarget>
    <SellAllAtTargetAndAfterReaching>Target 2,Target 3</SellAllAtTargetAndAfterReaching>
    <Symbol>OMG</Symbol>
    <StartingAmount>15</StartingAmount>
    <CurrentAmount>15</CurrentAmount>
    <UsedTargets />
    <CurrentRateUSD>14.66685640</CurrentRateUSD>
    <CurrentRateBTC>0.00096556</CurrentRateBTC>
    <MaxPercentageReached>13.28</MaxPercentageReached>
    <MaxBTCReached>0.00098702</MaxBTCReached>
    <TradeAtRateBTC>0.00095815</TradeAtRateBTC>
    <TradeAtRateUSD>11.8810600000095815</TradeAtRateUSD>
    <TradeAtDateTime>2017-12-24T08:15:19.332544-06:00</TradeAtDateTime>
    <OrderID>cba46215-aa62-463c-b6ca-8327ea5d2481</OrderID>
    <OrderCompleted>true</OrderCompleted>
    <IsActive>true</IsActive>
    <IsParent>true</IsParent>
    <IsBuyObject>true</IsBuyObject>
    <LastAutoSellTime>0001-01-01T00:00:00</LastAutoSellTime>
    <SoldAllTime>0001-01-01T00:00:00</SoldAllTime>
  </CryptoObject>
  <CryptoObject>
    <ID>59d2cf3a-ae07-47d1-a3fb-b908163c9c34</ID>
    <Exchange>Binance</Exchange>
    <SellType>ShortTerm</SellType>
    <Target1>0</Target1>
    <Target2>0</Target2>
    <Target3>0</Target3>
    <Target4>0</Target4>
    <UseTargetsInstreadOfPercentages>false</UseTargetsInstreadOfPercentages>
    <Symbol>ARK</Symbol>
    <StartingAmount>4.995</StartingAmount>
    <CurrentAmount>4.995</CurrentAmount>
    <UsedTargets />
    <CurrentRateUSD>7.3751761920000000</CurrentRateUSD>
    <CurrentRateBTC>0.00048640</CurrentRateBTC>
    <MaxPercentageReached>24.93</MaxPercentageReached>
    <MaxBTCReached>0.00051150</MaxBTCReached>
    <TradeAtRateBTC>0.00044440</TradeAtRateBTC>
    <TradeAtRateUSD>5.5794420000000000</TradeAtRateUSD>
    <TradeAtDateTime>2017-12-24T07:28:20.6910782-06:00</TradeAtDateTime>
    <OrderID>2893901</OrderID>
    <OrderCompleted>true</OrderCompleted>
    <IsActive>true</IsActive>
    <IsParent>true</IsParent>
    <IsBuyObject>true</IsBuyObject>
    <LastAutoSellTime>2017-12-26T07:26:54.5865498-06:00</LastAutoSellTime>
    <SoldAllTime>0001-01-01T00:00:00</SoldAllTime>
  </CryptoObject>
  <CryptoObject>
    <ID>4ddf203e-508f-4fd2-9a5c-ddc45cfbd9b9</ID>
    <Exchange>Bittrex</Exchange>
    <SellType>ShortTerm</SellType>
    <Target1>0</Target1>
    <Target2>0</Target2>
    <Target3>0</Target3>
    <Target4>0</Target4>
    <UseTargetsInstreadOfPercentages>false</UseTargetsInstreadOfPercentages>
    <Symbol>CURE</Symbol>
    <StartingAmount>200</StartingAmount>
    <CurrentAmount>0</CurrentAmount>
    <UsedTargets />
    <CurrentRateUSD>0</CurrentRateUSD>
    <CurrentRateBTC>0</CurrentRateBTC>
    <MaxPercentageReached>0</MaxPercentageReached>
    <MaxBTCReached>0</MaxBTCReached>
    <TradeAtRateBTC>0.00004067</TradeAtRateBTC>
    <TradeAtRateUSD>0.5167</TradeAtRateUSD>
    <TradeAtDateTime>2017-12-24T08:18:37.4657773-06:00</TradeAtDateTime>
    <OrderID>bfe08bba-798e-4fbe-895c-8393ff728e5d</OrderID>
    <OrderCompleted>true</OrderCompleted>
    <IsActive>true</IsActive>
    <IsParent>false</IsParent>
    <IsBuyObject>false</IsBuyObject>
    <LastAutoSellTime>0001-01-01T00:00:00</LastAutoSellTime>
    <SoldAllTime>0001-01-01T00:00:00</SoldAllTime>
  </CryptoObject>
  <CryptoObject>
    <ID>c56ec785-66d8-4967-80cb-69a96d31a66d</ID>
    <Exchange>Bittrex</Exchange>
    <SellType>ShortTerm</SellType>
    <Target1>0</Target1>
    <Target2>0</Target2>
    <Target3>0</Target3>
    <Target4>0</Target4>
    <UseTargetsInstreadOfPercentages>false</UseTargetsInstreadOfPercentages>
    <Symbol>AMP</Symbol>
    <StartingAmount>90</StartingAmount>
    <CurrentAmount>0</CurrentAmount>
    <UsedTargets />
    <CurrentRateUSD>0</CurrentRateUSD>
    <CurrentRateBTC>0</CurrentRateBTC>
    <MaxPercentageReached>0</MaxPercentageReached>
    <MaxBTCReached>0</MaxBTCReached>
    <TradeAtRateBTC>0.00005161</TradeAtRateBTC>
    <TradeAtRateUSD>0.6503</TradeAtRateUSD>
    <TradeAtDateTime>2017-12-24T11:57:39.440039-06:00</TradeAtDateTime>
    <OrderID>52fcf81b-271f-47b9-bd1b-4045d850fe7c</OrderID>
    <OrderCompleted>true</OrderCompleted>
    <IsActive>true</IsActive>
    <IsParent>false</IsParent>
    <IsBuyObject>false</IsBuyObject>
    <LastAutoSellTime>0001-01-01T00:00:00</LastAutoSellTime>
    <SoldAllTime>0001-01-01T00:00:00</SoldAllTime>
  </CryptoObject>
  <CryptoObject>
    <ID>9be399ac-29cb-4340-acb0-d65352b52f2c</ID>
    <Exchange>Bittrex</Exchange>
    <SellType>MidTerm</SellType>
    <Target1>0.00009330</Target1>
    <Target2>0.00015400</Target2>
    <Target3>0.00016400</Target3>
    <Target4>0.00020400</Target4>
    <UseTargetsInstreadOfPercentages>true</UseTargetsInstreadOfPercentages>
    <SellAllAtTarget>Target 4</SellAllAtTarget>
    <SellAllAtTargetAndAfterReaching>Target 2,Target 3</SellAllAtTargetAndAfterReaching>
    <Symbol>DCT</Symbol>
    <StartingAmount>1000</StartingAmount>
    <CurrentAmount>400</CurrentAmount>
    <UsedTargets>Mid_Target2,Mid_Target1,Mid_Target3</UsedTargets>
    <CurrentRateUSD>2.354450</CurrentRateUSD>
    <CurrentRateBTC>0.000155</CurrentRateBTC>
    <MaxPercentageReached>133.13</MaxPercentageReached>
    <MaxBTCReached>0.0001745</MaxBTCReached>
    <TradeAtRateBTC>0.00007484999</TradeAtRateBTC>
    <TradeAtRateUSD>1.19123759085</TradeAtRateUSD>
    <TradeAtDateTime>2017-12-26T09:05:11.3757085-06:00</TradeAtDateTime>
    <OrderID>a52c5309-a7e5-4d57-bccd-815003f3e59e</OrderID>
    <OrderCompleted>true</OrderCompleted>
    <IsActive>true</IsActive>
    <IsParent>true</IsParent>
    <IsBuyObject>true</IsBuyObject>
    <LastAutoSellTime>2017-12-27T01:57:55.4569687-06:00</LastAutoSellTime>
    <SoldAllTime>0001-01-01T00:00:00</SoldAllTime>
  </CryptoObject>
  <CryptoObject>
    <ID>b7692cd6-edc7-4856-9c70-37c689c4b716</ID>
    <Exchange>Bittrex</Exchange>
    <SellType>ShortTerm</SellType>
    <Target1>0.00000188</Target1>
    <Target2>0.00000206</Target2>
    <Target3>0.00000228</Target3>
    <Target4>0</Target4>
    <UseTargetsInstreadOfPercentages>false</UseTargetsInstreadOfPercentages>
    <Symbol>ABY</Symbol>
    <StartingAmount>614</StartingAmount>
    <CurrentAmount>0</CurrentAmount>
    <UsedTargets />
    <CurrentRateUSD>0.0258326852180207</CurrentRateUSD>
    <CurrentRateBTC>0.00000163</CurrentRateBTC>
    <MaxPercentageReached>0</MaxPercentageReached>
    <MaxBTCReached>0.00000163</MaxBTCReached>
    <TradeAtRateBTC>0.00000163</TradeAtRateBTC>
    <TradeAtRateUSD>0.0258326852180207</TradeAtRateUSD>
    <TradeAtDateTime>2017-12-26T10:46:18.1071168-06:00</TradeAtDateTime>
    <OrderID>86dd5403-7056-41d2-9f54-0734cf0428e7</OrderID>
    <OrderCompleted>true</OrderCompleted>
    <IsActive>false</IsActive>
    <IsParent>true</IsParent>
    <IsBuyObject>true</IsBuyObject>
    <LastAutoSellTime>2017-12-26T10:46:23.3045821-06:00</LastAutoSellTime>
    <SoldAllTime>2017-12-26T10:47:28.5324569-06:00</SoldAllTime>
  </CryptoObject>
  <CryptoObject>
    <ID>b7692cd6-edc7-4856-9c70-37c689c4b716</ID>
    <Exchange>Bittrex</Exchange>
    <SellType>ShortTerm</SellType>
    <Target1>0</Target1>
    <Target2>0</Target2>
    <Target3>0</Target3>
    <Target4>0</Target4>
    <UseTargetsInstreadOfPercentages>false</UseTargetsInstreadOfPercentages>
    <Symbol>ABY</Symbol>
    <StartingAmount>614</StartingAmount>
    <CurrentAmount>0</CurrentAmount>
    <UsedTargets />
    <CurrentRateUSD>0</CurrentRateUSD>
    <CurrentRateBTC>0</CurrentRateBTC>
    <MaxPercentageReached>0</MaxPercentageReached>
    <MaxBTCReached>0</MaxBTCReached>
    <TradeAtRateBTC>0.00000163</TradeAtRateBTC>
    <TradeAtRateUSD>0.0258</TradeAtRateUSD>
    <TradeAtDateTime>2017-12-26T10:46:26.0853648-06:00</TradeAtDateTime>
    <OrderID>7cc2d83f-e209-4a05-a9d6-1c21948e21d8</OrderID>
    <OrderCompleted>true</OrderCompleted>
    <IsActive>true</IsActive>
    <IsParent>false</IsParent>
    <IsBuyObject>false</IsBuyObject>
    <LastAutoSellTime>0001-01-01T00:00:00</LastAutoSellTime>
    <SoldAllTime>0001-01-01T00:00:00</SoldAllTime>
  </CryptoObject>
  <CryptoObject>
    <ID>0c4ac65b-1343-49a5-a751-911bac012419</ID>
    <Exchange>Bittrex</Exchange>
    <SellType>ShortTerm</SellType>
    <Target1>0.00274</Target1>
    <Target2>0.00280</Target2>
    <Target3>0.00295</Target3>
    <Target4>0</Target4>
    <UseTargetsInstreadOfPercentages>false</UseTargetsInstreadOfPercentages>
    <Symbol>ZEN</Symbol>
    <StartingAmount>10</StartingAmount>
    <CurrentAmount>0</CurrentAmount>
    <UsedTargets />
    <CurrentRateUSD>45.2989135507</CurrentRateUSD>
    <CurrentRateBTC>0.00307007</CurrentRateBTC>
    <MaxPercentageReached>16.70</MaxPercentageReached>
    <MaxBTCReached>0.00310628</MaxBTCReached>
    <TradeAtRateBTC>0.002664</TradeAtRateBTC>
    <TradeAtRateUSD>42.1984876446936</TradeAtRateUSD>
    <TradeAtDateTime>2017-12-26T10:49:48.0851659-06:00</TradeAtDateTime>
    <OrderID>6fe9ac34-7a36-495c-8f41-061919bf0fea</OrderID>
    <OrderCompleted>true</OrderCompleted>
    <IsActive>false</IsActive>
    <IsParent>true</IsParent>
    <IsBuyObject>true</IsBuyObject>
    <LastAutoSellTime>2017-12-26T18:10:59.0822946-06:00</LastAutoSellTime>
    <SoldAllTime>2017-12-27T12:01:45.2107813-06:00</SoldAllTime>
  </CryptoObject>
  <CryptoObject>
    <ID>0c4ac65b-1343-49a5-a751-911bac012419</ID>
    <Exchange>Bittrex</Exchange>
    <SellType>ShortTerm</SellType>
    <Target1>0</Target1>
    <Target2>0</Target2>
    <Target3>0</Target3>
    <Target4>0</Target4>
    <UseTargetsInstreadOfPercentages>false</UseTargetsInstreadOfPercentages>
    <Symbol>ZEN</Symbol>
    <StartingAmount>10</StartingAmount>
    <CurrentAmount>7</CurrentAmount>
    <UsedTargets />
    <CurrentRateUSD>0</CurrentRateUSD>
    <CurrentRateBTC>0</CurrentRateBTC>
    <MaxPercentageReached>0</MaxPercentageReached>
    <MaxBTCReached>0</MaxBTCReached>
    <TradeAtRateBTC>0.002664</TradeAtRateBTC>
    <TradeAtRateUSD>41.9766</TradeAtRateUSD>
    <TradeAtDateTime>2017-12-26T11:31:42.5975066-06:00</TradeAtDateTime>
    <OrderID>ba779a25-0b39-4f65-8aec-6a31a85ec840</OrderID>
    <OrderCompleted>true</OrderCompleted>
    <IsActive>true</IsActive>
    <IsParent>false</IsParent>
    <IsBuyObject>false</IsBuyObject>
    <LastAutoSellTime>0001-01-01T00:00:00</LastAutoSellTime>
    <SoldAllTime>0001-01-01T00:00:00</SoldAllTime>
  </CryptoObject>
  <CryptoObject>
    <ID>0c4ac65b-1343-49a5-a751-911bac012419</ID>
    <Exchange>Bittrex</Exchange>
    <SellType>ShortTerm</SellType>
    <Target1>0</Target1>
    <Target2>0</Target2>
    <Target3>0</Target3>
    <Target4>0</Target4>
    <UseTargetsInstreadOfPercentages>false</UseTargetsInstreadOfPercentages>
    <Symbol>ZEN</Symbol>
    <StartingAmount>7</StartingAmount>
    <CurrentAmount>4</CurrentAmount>
    <UsedTargets />
    <CurrentRateUSD>0</CurrentRateUSD>
    <CurrentRateBTC>0</CurrentRateBTC>
    <MaxPercentageReached>0</MaxPercentageReached>
    <MaxBTCReached>0</MaxBTCReached>
    <TradeAtRateBTC>0.00282844</TradeAtRateBTC>
    <TradeAtRateUSD>44.4914</TradeAtRateUSD>
    <TradeAtDateTime>2017-12-26T13:21:22.0126814-06:00</TradeAtDateTime>
    <OrderID>0fd83a89-ac68-488a-9f9e-052fd8d07a35</OrderID>
    <OrderCompleted>true</OrderCompleted>
    <IsActive>true</IsActive>
    <IsParent>false</IsParent>
    <IsBuyObject>false</IsBuyObject>
    <LastAutoSellTime>0001-01-01T00:00:00</LastAutoSellTime>
    <SoldAllTime>0001-01-01T00:00:00</SoldAllTime>
  </CryptoObject>
  <CryptoObject>
    <ID>0c4ac65b-1343-49a5-a751-911bac012419</ID>
    <Exchange>Bittrex</Exchange>
    <SellType>ShortTerm</SellType>
    <Target1>0</Target1>
    <Target2>0</Target2>
    <Target3>0</Target3>
    <Target4>0</Target4>
    <UseTargetsInstreadOfPercentages>false</UseTargetsInstreadOfPercentages>
    <Symbol>ZEN</Symbol>
    <StartingAmount>4</StartingAmount>
    <CurrentAmount>1</CurrentAmount>
    <UsedTargets />
    <CurrentRateUSD>0</CurrentRateUSD>
    <CurrentRateBTC>0</CurrentRateBTC>
    <MaxPercentageReached>0</MaxPercentageReached>
    <MaxBTCReached>0</MaxBTCReached>
    <TradeAtRateBTC>0.00274674</TradeAtRateBTC>
    <TradeAtRateUSD>42.7146</TradeAtRateUSD>
    <TradeAtDateTime>2017-12-26T18:11:05.1229991-06:00</TradeAtDateTime>
    <OrderID>2813a1f1-d548-4c96-b1f6-a3faa579d141</OrderID>
    <OrderCompleted>true</OrderCompleted>
    <IsActive>true</IsActive>
    <IsParent>false</IsParent>
    <IsBuyObject>false</IsBuyObject>
    <LastAutoSellTime>0001-01-01T00:00:00</LastAutoSellTime>
    <SoldAllTime>0001-01-01T00:00:00</SoldAllTime>
  </CryptoObject>
  <CryptoObject>
    <ID>9be399ac-29cb-4340-acb0-d65352b52f2c</ID>
    <Exchange>Bittrex</Exchange>
    <SellType>ShortTerm</SellType>
    <Target1>0</Target1>
    <Target2>0</Target2>
    <Target3>0</Target3>
    <Target4>0</Target4>
    <UseTargetsInstreadOfPercentages>false</UseTargetsInstreadOfPercentages>
    <Symbol>DCT</Symbol>
    <StartingAmount>1000</StartingAmount>
    <CurrentAmount>700</CurrentAmount>
    <UsedTargets />
    <CurrentRateUSD>0</CurrentRateUSD>
    <CurrentRateBTC>0</CurrentRateBTC>
    <MaxPercentageReached>0</MaxPercentageReached>
    <MaxBTCReached>0</MaxBTCReached>
    <TradeAtRateBTC>-1</TradeAtRateBTC>
    <TradeAtRateUSD>-1</TradeAtRateUSD>
    <TradeAtDateTime>2017-12-26T23:42:35.3701836-06:00</TradeAtDateTime>
    <OrderID>685f8eed-71e9-4640-8f75-25b38a34d3da</OrderID>
    <OrderCompleted>false</OrderCompleted>
    <IsActive>true</IsActive>
    <IsParent>false</IsParent>
    <IsBuyObject>false</IsBuyObject>
    <LastAutoSellTime>0001-01-01T00:00:00</LastAutoSellTime>
    <SoldAllTime>0001-01-01T00:00:00</SoldAllTime>
  </CryptoObject>
  <CryptoObject>
    <ID>9be399ac-29cb-4340-acb0-d65352b52f2c</ID>
    <Exchange>Bittrex</Exchange>
    <SellType>ShortTerm</SellType>
    <Target1>0</Target1>
    <Target2>0</Target2>
    <Target3>0</Target3>
    <Target4>0</Target4>
    <UseTargetsInstreadOfPercentages>false</UseTargetsInstreadOfPercentages>
    <Symbol>DCT</Symbol>
    <StartingAmount>700</StartingAmount>
    <CurrentAmount>400</CurrentAmount>
    <UsedTargets />
    <CurrentRateUSD>0</CurrentRateUSD>
    <CurrentRateBTC>0</CurrentRateBTC>
    <MaxPercentageReached>0</MaxPercentageReached>
    <MaxBTCReached>0</MaxBTCReached>
    <TradeAtRateBTC>0.00012891</TradeAtRateBTC>
    <TradeAtRateUSD>2.1141</TradeAtRateUSD>
    <TradeAtDateTime>2017-12-27T00:42:44.3959914-06:00</TradeAtDateTime>
    <OrderID>ad918dc1-3fda-414c-9ecf-bf045645a609</OrderID>
    <OrderCompleted>true</OrderCompleted>
    <IsActive>true</IsActive>
    <IsParent>false</IsParent>
    <IsBuyObject>false</IsBuyObject>
    <LastAutoSellTime>0001-01-01T00:00:00</LastAutoSellTime>
    <SoldAllTime>0001-01-01T00:00:00</SoldAllTime>
  </CryptoObject>
  <CryptoObject>
    <ID>9be399ac-29cb-4340-acb0-d65352b52f2c</ID>
    <Exchange>Bittrex</Exchange>
    <SellType>ShortTerm</SellType>
    <Target1>0</Target1>
    <Target2>0</Target2>
    <Target3>0</Target3>
    <Target4>0</Target4>
    <UseTargetsInstreadOfPercentages>false</UseTargetsInstreadOfPercentages>
    <Symbol>DCT</Symbol>
    <StartingAmount>400</StartingAmount>
    <CurrentAmount>100</CurrentAmount>
    <UsedTargets />
    <CurrentRateUSD>0</CurrentRateUSD>
    <CurrentRateBTC>0</CurrentRateBTC>
    <MaxPercentageReached>0</MaxPercentageReached>
    <MaxBTCReached>0</MaxBTCReached>
    <TradeAtRateBTC>0.00015498</TradeAtRateBTC>
    <TradeAtRateUSD>2.5029</TradeAtRateUSD>
    <TradeAtDateTime>2017-12-27T01:57:58.4256964-06:00</TradeAtDateTime>
    <OrderID>557ab1bf-9445-4429-9dd4-e02865d58b25</OrderID>
    <OrderCompleted>true</OrderCompleted>
    <IsActive>true</IsActive>
    <IsParent>false</IsParent>
    <IsBuyObject>false</IsBuyObject>
    <LastAutoSellTime>0001-01-01T00:00:00</LastAutoSellTime>
    <SoldAllTime>0001-01-01T00:00:00</SoldAllTime>
  </CryptoObject>
  <CryptoObject>
    <ID>933d3164-c186-4486-80bb-c27fd915efe0</ID>
    <Exchange>Bittrex</Exchange>
    <SellType>ShortTerm</SellType>
    <Target1>0.00008900</Target1>
    <Target2>0.00012900</Target2>
    <Target3>0.00013800</Target3>
    <Target4>0</Target4>
    <UseTargetsInstreadOfPercentages>true</UseTargetsInstreadOfPercentages>
    <SellAllAtTarget>Target 3</SellAllAtTarget>
    <SellAllAtTargetAndAfterReaching>Target 2,Target 3</SellAllAtTargetAndAfterReaching>
    <Symbol>CURE</Symbol>
    <StartingAmount>400</StartingAmount>
    <CurrentAmount>400</CurrentAmount>
    <UsedTargets />
    <CurrentRateUSD>0.83909560</CurrentRateUSD>
    <CurrentRateBTC>0.00005524</CurrentRateBTC>
    <MaxPercentageReached>7.54</MaxPercentageReached>
    <MaxBTCReached>0.00005888</MaxBTCReached>
    <TradeAtRateBTC>0.00005475</TradeAtRateBTC>
    <TradeAtRateUSD>0.80208750</TradeAtRateUSD>
    <TradeAtDateTime>2017-12-27T11:14:57.5664681-06:00</TradeAtDateTime>
    <OrderID>d84100f1-76f2-4f18-bd18-c36f0daf10d8</OrderID>
    <OrderCompleted>true</OrderCompleted>
    <IsActive>true</IsActive>
    <IsParent>true</IsParent>
    <IsBuyObject>true</IsBuyObject>
    <LastAutoSellTime>0001-01-01T00:00:00</LastAutoSellTime>
    <SoldAllTime>0001-01-01T00:00:00</SoldAllTime>
  </CryptoObject>
  <CryptoObject>
    <ID>7e45533e-042a-447e-aebc-0cfd6f7cfe4b</ID>
    <Exchange>Bittrex</Exchange>
    <SellType>LongTerm</SellType>
    <Target1>0</Target1>
    <Target2>0</Target2>
    <Target3>0</Target3>
    <Target4>0</Target4>
    <UseTargetsInstreadOfPercentages>false</UseTargetsInstreadOfPercentages>
    <SellAllAtTarget />
    <SellAllAtTargetAndAfterReaching>,</SellAllAtTargetAndAfterReaching>
    <Symbol>ADX</Symbol>
    <StartingAmount>30</StartingAmount>
    <CurrentAmount>30</CurrentAmount>
    <UsedTargets />
    <CurrentRateUSD>3.06321540</CurrentRateUSD>
    <CurrentRateBTC>0.00020166</CurrentRateBTC>
    <MaxPercentageReached>0.91</MaxPercentageReached>
    <MaxBTCReached>0.000211</MaxBTCReached>
    <TradeAtRateBTC>0.00020973</TradeAtRateBTC>
    <TradeAtRateUSD>3.1237186199979027</TradeAtRateUSD>
    <TradeAtDateTime>2017-12-27T11:45:18.2859381-06:00</TradeAtDateTime>
    <OrderID>3430aa8e-38da-4eea-b2d3-d7e3c9da6762</OrderID>
    <OrderCompleted>true</OrderCompleted>
    <IsActive>true</IsActive>
    <IsParent>true</IsParent>
    <IsBuyObject>true</IsBuyObject>
    <LastAutoSellTime>0001-01-01T00:00:00</LastAutoSellTime>
    <SoldAllTime>0001-01-01T00:00:00</SoldAllTime>
  </CryptoObject>
  <CryptoObject>
    <ID>0c4ac65b-1343-49a5-a751-911bac012419</ID>
    <Exchange>Bittrex</Exchange>
    <SellType>ShortTerm</SellType>
    <Target1>0</Target1>
    <Target2>0</Target2>
    <Target3>0</Target3>
    <Target4>0</Target4>
    <UseTargetsInstreadOfPercentages>false</UseTargetsInstreadOfPercentages>
    <Symbol>ZEN</Symbol>
    <StartingAmount>1</StartingAmount>
    <CurrentAmount>0</CurrentAmount>
    <UsedTargets />
    <CurrentRateUSD>0</CurrentRateUSD>
    <CurrentRateBTC>0</CurrentRateBTC>
    <MaxPercentageReached>0</MaxPercentageReached>
    <MaxBTCReached>0</MaxBTCReached>
    <TradeAtRateBTC>0.003071</TradeAtRateBTC>
    <TradeAtRateUSD>45.3126</TradeAtRateUSD>
    <TradeAtDateTime>2017-12-27T12:01:43.0477137-06:00</TradeAtDateTime>
    <OrderID>2b2e8168-ec7d-417a-94a5-a2181fc5eb53</OrderID>
    <OrderCompleted>true</OrderCompleted>
    <IsActive>true</IsActive>
    <IsParent>false</IsParent>
    <IsBuyObject>false</IsBuyObject>
    <LastAutoSellTime>0001-01-01T00:00:00</LastAutoSellTime>
    <SoldAllTime>0001-01-01T00:00:00</SoldAllTime>
  </CryptoObject>
  <CryptoObject>
    <ID>0a578c08-faf7-4d26-ad4a-2fbe8b785f15</ID>
    <Exchange>Bittrex</Exchange>
    <SellType>MidTerm</SellType>
    <Target1>0.0012000</Target1>
    <Target2>0.0014000</Target2>
    <Target3>0.0015000</Target3>
    <Target4>0</Target4>
    <UseTargetsInstreadOfPercentages>true</UseTargetsInstreadOfPercentages>
    <SellAllAtTarget>Target 3</SellAllAtTarget>
    <SellAllAtTargetAndAfterReaching>Target 2,Target 3</SellAllAtTargetAndAfterReaching>
    <Symbol>MCO</Symbol>
    <StartingAmount>30</StartingAmount>
    <CurrentAmount>30</CurrentAmount>
    <UsedTargets />
    <CurrentRateUSD>16.71143040</CurrentRateUSD>
    <CurrentRateBTC>0.00110016</CurrentRateBTC>
    <MaxPercentageReached>0.54</MaxPercentageReached>
    <MaxBTCReached>0.0011137</MaxBTCReached>
    <TradeAtRateBTC>0.0011128596666666666666666667</TradeAtRateBTC>
    <TradeAtRateUSD>16.444397248968136770000000493</TradeAtRateUSD>
    <TradeAtDateTime>2017-12-27T14:53:28.520907-06:00</TradeAtDateTime>
    <OrderID>73975d4a-ac9a-42e2-85b0-83490ad307df</OrderID>
    <OrderCompleted>true</OrderCompleted>
    <IsActive>true</IsActive>
    <IsParent>true</IsParent>
    <IsBuyObject>true</IsBuyObject>
    <LastAutoSellTime>0001-01-01T00:00:00</LastAutoSellTime>
    <SoldAllTime>0001-01-01T00:00:00</SoldAllTime>
  </CryptoObject>
  <CryptoObject>
    <ID>4244667f-4a0f-4c58-88d0-f3e500cd7cb2</ID>
    <Exchange>Bittrex</Exchange>
    <SellType>MidTerm</SellType>
    <Target1>0.0000950</Target1>
    <Target2>0.0000975</Target2>
    <Target3>0.00001050</Target3>
    <Target4>0.00001125</Target4>
    <UseTargetsInstreadOfPercentages>true</UseTargetsInstreadOfPercentages>
    <SellAllAtTarget>Target 4</SellAllAtTarget>
    <SellAllAtTargetAndAfterReaching>Target 2,Target 3</SellAllAtTargetAndAfterReaching>
    <Symbol>NXT</Symbol>
    <StartingAmount>85</StartingAmount>
    <CurrentAmount>85</CurrentAmount>
    <UsedTargets />
    <CurrentRateUSD>1.18117440</CurrentRateUSD>
    <CurrentRateBTC>0.00007776</CurrentRateBTC>
    <MaxPercentageReached>0.01</MaxPercentageReached>
    <MaxBTCReached>0.00008449</MaxBTCReached>
    <TradeAtRateBTC>0.00008448</TradeAtRateBTC>
    <TradeAtRateUSD>1.24439040</TradeAtRateUSD>
    <TradeAtDateTime>2017-12-27T15:00:34.2648868-06:00</TradeAtDateTime>
    <OrderID>8d0c9231-145f-4eeb-a71c-06d52b3b8c00</OrderID>
    <OrderCompleted>true</OrderCompleted>
    <IsActive>true</IsActive>
    <IsParent>true</IsParent>
    <IsBuyObject>true</IsBuyObject>
    <LastAutoSellTime>0001-01-01T00:00:00</LastAutoSellTime>
    <SoldAllTime>0001-01-01T00:00:00</SoldAllTime>
  </CryptoObject>
  <CryptoObject>
    <ID>9502a1e2-dba8-4455-b02a-7df8288e0d72</ID>
    <Exchange>Bittrex</Exchange>
    <SellType>MidTerm</SellType>
    <Target1>0</Target1>
    <Target2>0</Target2>
    <Target3>0</Target3>
    <Target4>0</Target4>
    <UseTargetsInstreadOfPercentages>false</UseTargetsInstreadOfPercentages>
    <SellAllAtTarget />
    <SellAllAtTargetAndAfterReaching>,</SellAllAtTargetAndAfterReaching>
    <Symbol>CVC</Symbol>
    <StartingAmount>400</StartingAmount>
    <CurrentAmount>400</CurrentAmount>
    <UsedTargets />
    <CurrentRateUSD>0.98719810</CurrentRateUSD>
    <CurrentRateBTC>0.00006499</CurrentRateBTC>
    <MaxPercentageReached>0.67</MaxPercentageReached>
    <MaxBTCReached>0.0000659</MaxBTCReached>
    <TradeAtRateBTC>0.00006576</TradeAtRateBTC>
    <TradeAtRateUSD>0.96864480</TradeAtRateUSD>
    <TradeAtDateTime>2017-12-27T15:03:33.2781601-06:00</TradeAtDateTime>
    <OrderID>db36e879-acf4-4a30-8cf7-ea170c09709d</OrderID>
    <OrderCompleted>true</OrderCompleted>
    <IsActive>true</IsActive>
    <IsParent>true</IsParent>
    <IsBuyObject>true</IsBuyObject>
    <LastAutoSellTime>0001-01-01T00:00:00</LastAutoSellTime>
    <SoldAllTime>0001-01-01T00:00:00</SoldAllTime>
  </CryptoObject>
  <CryptoObject>
    <ID>d289d0ce-ccb5-4a14-85ae-58771984046b</ID>
    <Exchange>Bittrex</Exchange>
    <SellType>MidTerm</SellType>
    <Target1>0</Target1>
    <Target2>0</Target2>
    <Target3>0</Target3>
    <Target4>0</Target4>
    <UseTargetsInstreadOfPercentages>false</UseTargetsInstreadOfPercentages>
    <SellAllAtTarget />
    <SellAllAtTargetAndAfterReaching>,</SellAllAtTargetAndAfterReaching>
    <Symbol>GAME</Symbol>
    <StartingAmount>25</StartingAmount>
    <CurrentAmount>25</CurrentAmount>
    <UsedTargets />
    <CurrentRateUSD>4.20747810</CurrentRateUSD>
    <CurrentRateBTC>0.00027699</CurrentRateBTC>
    <MaxPercentageReached>2.11</MaxPercentageReached>
    <MaxBTCReached>0.00027921</MaxBTCReached>
    <TradeAtRateBTC>0.00027367</TradeAtRateBTC>
    <TradeAtRateUSD>4.08206172</TradeAtRateUSD>
    <TradeAtDateTime>2017-12-27T15:09:35.6954627-06:00</TradeAtDateTime>
    <OrderID>66a23108-1cfd-4d7c-9700-14b2de58bc1c</OrderID>
    <OrderCompleted>true</OrderCompleted>
    <IsActive>true</IsActive>
    <IsParent>true</IsParent>
    <IsBuyObject>true</IsBuyObject>
    <LastAutoSellTime>0001-01-01T00:00:00</LastAutoSellTime>
    <SoldAllTime>0001-01-01T00:00:00</SoldAllTime>
  </CryptoObject>
</ArrayOfCryptoObject>